{"ticker":"SWDA","name":"SWDA","categoria":"ADVICE","is_bond":false,"updated":"19/05/2026 18:19","bars":[{"time":1716188400,"open":92.51,"high":92.51,"low":92.15,"close":92.51,"volume":123060},{"time":1716274800,"open":92.28,"high":92.35,"low":92.08,"close":92.28,"volume":36203},{"time":1716361200,"open":92.37,"high":92.43,"low":92.24,"close":92.37,"volume":38302},{"time":1716447600,"open":92.37,"high":92.87,"low":92.12,"close":92.37,"volume":46402},{"time":1716534000,"open":92.08,"high":92.16,"low":91.65,"close":92.08,"volume":69990},{"time":1716793200,"open":92.22,"high":92.22,"low":91.99,"close":92.22,"volume":62780},{"time":1716879600,"open":91.88,"high":92.3,"low":91.85,"close":91.88,"volume":60931},{"time":1716966000,"open":91.52,"high":91.78,"low":91.28,"close":91.52,"volume":42784},{"time":1717052400,"open":91.27,"high":91.44,"low":91.1,"close":91.27,"volume":53679},{"time":1717138800,"open":90.69,"high":91.26,"low":90.61,"close":90.69,"volume":87797},{"time":1717398000,"open":91.36,"high":92.05,"low":91.33,"close":91.36,"volume":98422},{"time":1717484400,"open":91.17,"high":91.72,"low":90.98,"close":91.17,"volume":42534},{"time":1717570800,"open":92.27,"high":92.27,"low":91.65,"close":92.27,"volume":34493},{"time":1717657200,"open":92.57,"high":92.78,"low":92.4,"close":92.57,"volume":43835},{"time":1717743600,"open":93.09,"high":93.24,"low":92.32,"close":93.09,"volume":47180},{"time":1718002800,"open":93.48,"high":93.48,"low":92.94,"close":93.48,"volume":72851},{"time":1718089200,"open":93.32,"high":93.44,"low":92.99,"close":93.32,"volume":42377},{"time":1718175600,"open":93.81,"high":94.0,"low":93.5,"close":93.81,"volume":58167},{"time":1718262000,"open":93.78,"high":94.03,"low":93.58,"close":93.78,"volume":58998},{"time":1718348400,"open":94.07,"high":94.33,"low":93.74,"close":94.07,"volume":52340},{"time":1718607600,"open":94.09,"high":94.34,"low":93.85,"close":94.09,"volume":66017},{"time":1718694000,"open":94.6,"high":94.73,"low":94.46,"close":94.6,"volume":64443},{"time":1718780400,"open":94.73,"high":94.91,"low":94.65,"close":94.73,"volume":65562},{"time":1718866800,"open":95.11,"high":95.29,"low":94.94,"close":95.11,"volume":149526},{"time":1718953200,"open":94.76,"high":95.08,"low":94.52,"close":94.76,"volume":113316},{"time":1719212400,"open":94.94,"high":94.97,"low":94.47,"close":94.94,"volume":41414},{"time":1719298800,"open":94.89,"high":94.96,"low":94.5,"close":94.89,"volume":34799},{"time":1719385200,"open":94.83,"high":95.43,"low":94.8,"close":94.83,"volume":45356},{"time":1719471600,"open":94.83,"high":95.09,"low":94.78,"close":94.83,"volume":81643},{"time":1719558000,"open":95.18,"high":95.64,"low":95.1,"close":95.18,"volume":55045},{"time":1719817200,"open":94.65,"high":94.9,"low":94.3,"close":94.65,"volume":93733},{"time":1719903600,"open":94.8,"high":94.8,"low":94.28,"close":94.8,"volume":64349},{"time":1719990000,"open":95.09,"high":95.5,"low":94.92,"close":95.09,"volume":26665},{"time":1720076400,"open":95.28,"high":95.55,"low":95.28,"close":95.28,"volume":27147},{"time":1720162800,"open":95.34,"high":95.46,"low":95.14,"close":95.34,"volume":57020},{"time":1720422000,"open":95.5,"high":95.68,"low":95.35,"close":95.5,"volume":80971},{"time":1720508400,"open":95.65,"high":95.84,"low":95.57,"close":95.65,"volume":88315},{"time":1720594800,"open":96.05,"high":96.05,"low":95.65,"close":96.05,"volume":60438},{"time":1720681200,"open":95.87,"high":96.5,"low":95.87,"close":95.87,"volume":55398},{"time":1720767600,"open":96.32,"high":96.36,"low":95.69,"close":96.32,"volume":95494},{"time":1721026800,"open":96.34,"high":96.53,"low":96.1,"close":96.34,"volume":118345},{"time":1721113200,"open":96.48,"high":96.66,"low":95.94,"close":96.48,"volume":45879},{"time":1721199600,"open":95.49,"high":96.27,"low":95.4,"close":95.49,"volume":65831},{"time":1721286000,"open":94.91,"high":95.82,"low":94.91,"close":94.91,"volume":83988},{"time":1721372400,"open":94.36,"high":94.97,"low":94.34,"close":94.36,"volume":88768},{"time":1721631600,"open":94.8,"high":95.21,"low":94.49,"close":94.8,"volume":62028},{"time":1721718000,"open":95.68,"high":95.7,"low":94.92,"close":95.68,"volume":53400},{"time":1721804400,"open":94.02,"high":94.9,"low":93.92,"close":94.02,"volume":96098},{"time":1721890800,"open":93.56,"high":93.72,"low":92.72,"close":93.56,"volume":118936},{"time":1721977200,"open":93.71,"high":93.9,"low":93.29,"close":93.71,"volume":64776},{"time":1722236400,"open":93.89,"high":94.77,"low":93.89,"close":93.89,"volume":77451},{"time":1722322800,"open":93.98,"high":94.71,"low":93.9,"close":93.98,"volume":62466},{"time":1722409200,"open":95.37,"high":95.39,"low":94.77,"close":95.37,"volume":65078},{"time":1722495600,"open":94.44,"high":95.84,"low":94.44,"close":94.44,"volume":135259},{"time":1722582000,"open":90.61,"high":93.11,"low":90.4,"close":90.61,"volume":149839},{"time":1722841200,"open":88.61,"high":88.85,"low":86.31,"close":88.61,"volume":313012},{"time":1722927600,"open":89.38,"high":89.83,"low":88.52,"close":89.38,"volume":204323},{"time":1723014000,"open":90.64,"high":90.97,"low":89.68,"close":90.64,"volume":100985},{"time":1723100400,"open":90.66,"high":90.75,"low":88.64,"close":90.66,"volume":77813},{"time":1723186800,"open":91.01,"high":91.43,"low":90.57,"close":91.01,"volume":77233},{"time":1723446000,"open":91.18,"high":91.58,"low":90.94,"close":91.18,"volume":65668},{"time":1723532400,"open":92.07,"high":92.09,"low":91.31,"close":92.07,"volume":173527},{"time":1723618800,"open":92.3,"high":92.3,"low":91.62,"close":92.3,"volume":38005},{"time":1723791600,"open":94.05,"high":94.43,"low":93.68,"close":94.05,"volume":68327},{"time":1724050800,"open":94.3,"high":94.33,"low":93.79,"close":94.3,"volume":40581},{"time":1724137200,"open":94.08,"high":94.74,"low":93.99,"close":94.08,"volume":81396},{"time":1724223600,"open":94.18,"high":94.58,"low":94.05,"close":94.18,"volume":34040},{"time":1724310000,"open":94.34,"high":94.81,"low":94.3,"close":94.34,"volume":24955},{"time":1724396400,"open":94.37,"high":94.75,"low":93.98,"close":94.37,"volume":40939},{"time":1724655600,"open":94.31,"high":94.87,"low":94.23,"close":94.31,"volume":28345},{"time":1724742000,"open":94.35,"high":94.58,"low":94.08,"close":94.35,"volume":32142},{"time":1724828400,"open":94.36,"high":94.96,"low":94.34,"close":94.36,"volume":55519},{"time":1724914800,"open":95.42,"high":95.6,"low":94.41,"close":95.42,"volume":45874},{"time":1725001200,"open":95.07,"high":95.53,"low":95.07,"close":95.07,"volume":44344},{"time":1725260400,"open":95.7,"high":95.75,"low":95.35,"close":95.7,"volume":36587},{"time":1725346800,"open":94.72,"high":95.85,"low":94.46,"close":94.72,"volume":86261},{"time":1725433200,"open":93.6,"high":93.87,"low":93.32,"close":93.6,"volume":60545},{"time":1725519600,"open":92.95,"high":93.8,"low":92.95,"close":92.95,"volume":53724},{"time":1725606000,"open":91.75,"high":93.44,"low":91.62,"close":91.75,"volume":105884},{"time":1725865200,"open":92.82,"high":92.97,"low":92.34,"close":92.82,"volume":74910},{"time":1725951600,"open":93.0,"high":93.27,"low":92.72,"close":93.0,"volume":42451},{"time":1726038000,"open":92.56,"high":93.47,"low":92.13,"close":92.56,"volume":92105},{"time":1726124400,"open":94.29,"high":94.6,"low":93.9,"close":94.29,"volume":50177},{"time":1726210800,"open":94.99,"high":95.0,"low":94.45,"close":94.99,"volume":37747},{"time":1726470000,"open":94.58,"high":94.93,"low":94.34,"close":94.58,"volume":89645},{"time":1726556400,"open":95.13,"high":95.31,"low":94.85,"close":95.13,"volume":55165},{"time":1726642800,"open":94.68,"high":94.97,"low":94.55,"close":94.68,"volume":55679},{"time":1726729200,"open":95.96,"high":96.2,"low":95.36,"close":95.96,"volume":51856},{"time":1726815600,"open":95.41,"high":95.81,"low":95.2,"close":95.41,"volume":56696},{"time":1727074800,"open":96.0,"high":96.12,"low":95.56,"close":96.0,"volume":61409},{"time":1727161200,"open":96.04,"high":96.38,"low":95.69,"close":96.04,"volume":56119},{"time":1727247600,"open":96.05,"high":96.09,"low":95.57,"close":96.05,"volume":52858},{"time":1727334000,"open":96.33,"high":97.12,"low":96.3,"close":96.33,"volume":80605},{"time":1727420400,"open":96.63,"high":96.79,"low":96.45,"close":96.63,"volume":59084},{"time":1727679600,"open":96.39,"high":96.55,"low":95.85,"close":96.39,"volume":66418},{"time":1727766000,"open":96.58,"high":97.34,"low":96.18,"close":96.58,"volume":113952},{"time":1727852400,"open":96.89,"high":96.89,"low":96.21,"close":96.89,"volume":84673},{"time":1727938800,"open":96.7,"high":96.82,"low":96.26,"close":96.7,"volume":65416},{"time":1728025200,"open":97.31,"high":97.89,"low":96.54,"close":97.31,"volume":105249},{"time":1728284400,"open":97.57,"high":97.78,"low":97.28,"close":97.57,"volume":56632},{"time":1728370800,"open":97.54,"high":97.6,"low":96.68,"close":97.54,"volume":55613},{"time":1728457200,"open":98.27,"high":98.27,"low":97.41,"close":98.27,"volume":49112},{"time":1728543600,"open":98.47,"high":98.53,"low":98.05,"close":98.47,"volume":53290},{"time":1728630000,"open":98.82,"high":98.94,"low":98.09,"close":98.82,"volume":46808},{"time":1728889200,"open":99.59,"high":99.76,"low":98.94,"close":99.59,"volume":87332},{"time":1728975600,"open":99.41,"high":100.03,"low":99.26,"close":99.41,"volume":137097},{"time":1729062000,"open":99.36,"high":99.47,"low":99.03,"close":99.36,"volume":66234},{"time":1729148400,"open":100.24,"high":100.75,"low":99.79,"close":100.24,"volume":81687},{"time":1729234800,"open":100.1,"high":100.28,"low":99.88,"close":100.1,"volume":58067},{"time":1729494000,"open":99.74,"high":100.27,"low":99.7,"close":99.74,"volume":76713},{"time":1729580400,"open":99.84,"high":99.96,"low":99.45,"close":99.84,"volume":61286},{"time":1729666800,"open":99.51,"high":100.22,"low":99.46,"close":99.51,"volume":53622},{"time":1729753200,"open":99.42,"high":99.94,"low":99.38,"close":99.42,"volume":62556},{"time":1729839600,"open":99.75,"high":99.95,"low":99.27,"close":99.75,"volume":596897},{"time":1730102400,"open":99.68,"high":99.93,"low":99.45,"close":99.68,"volume":48053},{"time":1730188800,"open":99.78,"high":99.91,"low":99.56,"close":99.78,"volume":44811},{"time":1730275200,"open":99.28,"high":99.8,"low":99.1,"close":99.28,"volume":56550},{"time":1730361600,"open":97.55,"high":98.5,"low":97.37,"close":97.55,"volume":68852},{"time":1730448000,"open":98.3,"high":98.44,"low":97.45,"close":98.3,"volume":88217},{"time":1730707200,"open":97.46,"high":97.8,"low":97.25,"close":97.46,"volume":75197},{"time":1730793600,"open":97.93,"high":98.0,"low":97.33,"close":97.93,"volume":62341},{"time":1730880000,"open":101.02,"high":101.89,"low":100.63,"close":101.02,"volume":159759},{"time":1730966400,"open":101.67,"high":101.72,"low":101.29,"close":101.67,"volume":81863},{"time":1731052800,"open":102.36,"high":102.36,"low":101.47,"close":102.36,"volume":53510},{"time":1731312000,"open":103.47,"high":103.66,"low":103.01,"close":103.47,"volume":80352},{"time":1731398400,"open":103.1,"high":103.5,"low":103.04,"close":103.1,"volume":98827},{"time":1731484800,"open":103.48,"high":103.48,"low":102.5,"close":103.48,"volume":54613},{"time":1731571200,"open":103.43,"high":104.15,"low":103.22,"close":103.43,"volume":56234},{"time":1731657600,"open":102.15,"high":102.71,"low":102.08,"close":102.15,"volume":100110},{"time":1731916800,"open":102.38,"high":102.38,"low":101.76,"close":102.38,"volume":59071},{"time":1732003200,"open":102.27,"high":102.46,"low":101.13,"close":102.27,"volume":58208},{"time":1732089600,"open":102.37,"high":102.92,"low":102.08,"close":102.37,"volume":59046},{"time":1732176000,"open":103.72,"high":103.73,"low":102.43,"close":103.72,"volume":100898},{"time":1732262400,"open":104.89,"high":105.1,"low":103.91,"close":104.89,"volume":92756},{"time":1732521600,"open":104.68,"high":105.17,"low":104.46,"close":104.68,"volume":139358},{"time":1732608000,"open":104.8,"high":104.86,"low":104.15,"close":104.8,"volume":49128},{"time":1732694400,"open":103.94,"high":104.77,"low":103.85,"close":103.94,"volume":75749},{"time":1732780800,"open":104.41,"high":104.54,"low":104.25,"close":104.41,"volume":49469},{"time":1732867200,"open":104.84,"high":104.85,"low":104.22,"close":104.84,"volume":119858},{"time":1733126400,"open":105.71,"high":105.8,"low":105.04,"close":105.71,"volume":116212},{"time":1733212800,"open":105.65,"high":105.77,"low":105.44,"close":105.65,"volume":62526},{"time":1733299200,"open":105.94,"high":106.4,"low":105.76,"close":105.94,"volume":105225},{"time":1733385600,"open":105.84,"high":106.25,"low":105.7,"close":105.84,"volume":92468},{"time":1733472000,"open":105.9,"high":106.17,"low":105.38,"close":105.9,"volume":72595},{"time":1733731200,"open":105.55,"high":106.15,"low":105.23,"close":105.55,"volume":58082},{"time":1733817600,"open":105.74,"high":105.93,"low":105.41,"close":105.74,"volume":43386},{"time":1733904000,"open":106.37,"high":106.4,"low":105.5,"close":106.37,"volume":55383},{"time":1733990400,"open":106.15,"high":106.43,"low":105.89,"close":106.15,"volume":80962},{"time":1734076800,"open":105.6,"high":106.25,"low":105.34,"close":105.6,"volume":48594},{"time":1734336000,"open":105.8,"high":105.95,"low":105.39,"close":105.8,"volume":91970},{"time":1734422400,"open":105.48,"high":105.76,"low":105.15,"close":105.48,"volume":76006},{"time":1734508800,"open":105.7,"high":105.9,"low":105.34,"close":105.7,"volume":59685},{"time":1734595200,"open":103.99,"high":104.3,"low":103.5,"close":103.99,"volume":132405},{"time":1734681600,"open":104.2,"high":104.2,"low":101.93,"close":104.2,"volume":138467},{"time":1734940800,"open":104.01,"high":104.38,"low":103.7,"close":104.01,"volume":79229},{"time":1735286400,"open":104.5,"high":105.33,"low":104.2,"close":104.5,"volume":69023},{"time":1735545600,"open":103.93,"high":104.52,"low":103.25,"close":103.93,"volume":90177},{"time":1735804800,"open":105.3,"high":105.3,"low":104.26,"close":105.3,"volume":155642},{"time":1735891200,"open":105.12,"high":105.15,"low":104.48,"close":105.12,"volume":79281},{"time":1736150400,"open":105.79,"high":105.84,"low":105.0,"close":105.79,"volume":57293},{"time":1736236800,"open":105.02,"high":105.62,"low":104.8,"close":105.02,"volume":90442},{"time":1736323200,"open":105.08,"high":105.39,"low":104.6,"close":105.08,"volume":100941},{"time":1736409600,"open":105.15,"high":105.16,"low":104.77,"close":105.15,"volume":39134},{"time":1736496000,"open":104.12,"high":105.17,"low":103.95,"close":104.12,"volume":88611},{"time":1736755200,"open":103.99,"high":104.3,"low":103.46,"close":103.99,"volume":79553},{"time":1736841600,"open":103.83,"high":104.8,"low":103.67,"close":103.83,"volume":61408},{"time":1736928000,"open":105.45,"high":105.6,"low":103.86,"close":105.45,"volume":100362},{"time":1737014400,"open":105.77,"high":106.24,"low":105.6,"close":105.77,"volume":81968},{"time":1737100800,"open":106.71,"high":106.86,"low":105.89,"close":106.71,"volume":95353},{"time":1737360000,"open":106.16,"high":106.7,"low":105.99,"close":106.16,"volume":85180},{"time":1737446400,"open":106.26,"high":106.73,"low":106.11,"close":106.26,"volume":64032},{"time":1737532800,"open":107.18,"high":107.18,"low":106.63,"close":107.18,"volume":91972},{"time":1737619200,"open":107.33,"high":107.88,"low":106.86,"close":107.33,"volume":73457},{"time":1737705600,"open":106.85,"high":107.22,"low":106.68,"close":106.85,"volume":97965},{"time":1737964800,"open":105.12,"high":105.67,"low":103.98,"close":105.12,"volume":158142},{"time":1738051200,"open":106.48,"high":106.78,"low":105.92,"close":106.48,"volume":81858},{"time":1738137600,"open":106.79,"high":107.42,"low":106.77,"close":106.79,"volume":136617},{"time":1738224000,"open":107.08,"high":107.5,"low":106.82,"close":107.08,"volume":67736},{"time":1738310400,"open":108.19,"high":108.45,"low":107.89,"close":108.19,"volume":128805},{"time":1738569600,"open":107.25,"high":107.28,"low":106.37,"close":107.25,"volume":255619},{"time":1738656000,"open":107.22,"high":107.22,"low":106.4,"close":107.22,"volume":80791},{"time":1738742400,"open":106.9,"high":106.9,"low":106.35,"close":106.9,"volume":78616},{"time":1738828800,"open":108.14,"high":108.28,"low":107.86,"close":108.14,"volume":95652},{"time":1738915200,"open":107.93,"high":108.39,"low":107.7,"close":107.93,"volume":91418},{"time":1739174400,"open":108.52,"high":108.66,"low":108.07,"close":108.52,"volume":105062},{"time":1739260800,"open":108.27,"high":108.44,"low":108.06,"close":108.27,"volume":119381},{"time":1739347200,"open":107.56,"high":108.39,"low":107.33,"close":107.56,"volume":132278},{"time":1739433600,"open":108.11,"high":108.23,"low":107.37,"close":108.11,"volume":109392},{"time":1739520000,"open":107.88,"high":108.33,"low":107.8,"close":107.88,"volume":70564},{"time":1739779200,"open":108.4,"high":108.49,"low":108.22,"close":108.4,"volume":59165},{"time":1739865600,"open":108.48,"high":108.93,"low":108.4,"close":108.48,"volume":115418},{"time":1739952000,"open":108.83,"high":108.95,"low":108.36,"close":108.83,"volume":106319},{"time":1740038400,"open":107.76,"high":108.82,"low":107.64,"close":107.76,"volume":94443},{"time":1740124800,"open":107.85,"high":108.37,"low":107.65,"close":107.85,"volume":84104},{"time":1740384000,"open":106.64,"high":107.23,"low":106.06,"close":106.64,"volume":147102},{"time":1740470400,"open":105.03,"high":106.4,"low":104.88,"close":105.03,"volume":99555},{"time":1740556800,"open":106.39,"high":106.63,"low":105.86,"close":106.39,"volume":83562},{"time":1740643200,"open":106.6,"high":106.79,"low":105.71,"close":106.6,"volume":137874},{"time":1740729600,"open":105.43,"high":105.73,"low":104.75,"close":105.43,"volume":97200},{"time":1740988800,"open":105.74,"high":106.8,"low":105.62,"close":105.74,"volume":234628},{"time":1741075200,"open":102.25,"high":104.42,"low":102.02,"close":102.25,"volume":314796},{"time":1741161600,"open":100.74,"high":102.55,"low":100.74,"close":100.74,"volume":157773},{"time":1741248000,"open":101.06,"high":101.66,"low":100.23,"close":101.06,"volume":128675},{"time":1741334400,"open":99.17,"high":100.3,"low":99.06,"close":99.17,"volume":178782},{"time":1741593600,"open":98.47,"high":100.05,"low":98.13,"close":98.47,"volume":227772},{"time":1741680000,"open":96.41,"high":97.87,"low":96.07,"close":96.41,"volume":270363},{"time":1741766400,"open":97.4,"high":97.99,"low":96.32,"close":97.4,"volume":417517},{"time":1741852800,"open":96.74,"high":97.75,"low":96.6,"close":96.74,"volume":121944},{"time":1741939200,"open":97.8,"high":98.11,"low":96.8,"close":97.8,"volume":117281},{"time":1742198400,"open":98.24,"high":98.66,"low":97.68,"close":98.24,"volume":172069},{"time":1742284800,"open":97.87,"high":98.73,"low":97.54,"close":97.87,"volume":168644},{"time":1742371200,"open":98.86,"high":99.01,"low":97.95,"close":98.86,"volume":61568},{"time":1742457600,"open":99.19,"high":99.94,"low":98.6,"close":99.19,"volume":113139},{"time":1742544000,"open":98.97,"high":99.14,"low":98.27,"close":98.97,"volume":93154},{"time":1742803200,"open":100.7,"high":100.8,"low":99.81,"close":100.7,"volume":128563},{"time":1742889600,"open":100.83,"high":101.08,"low":100.65,"close":100.83,"volume":92146},{"time":1742976000,"open":100.34,"high":101.26,"low":100.27,"close":100.34,"volume":116954},{"time":1743062400,"open":99.97,"high":100.34,"low":99.37,"close":99.97,"volume":100593},{"time":1743148800,"open":97.83,"high":99.72,"low":97.75,"close":97.83,"volume":129506},{"time":1743404400,"open":97.11,"high":97.15,"low":96.15,"close":97.11,"volume":164032},{"time":1743490800,"open":98.44,"high":98.84,"low":97.2,"close":98.44,"volume":281429},{"time":1743577200,"open":98.34,"high":98.35,"low":97.2,"close":98.34,"volume":131083},{"time":1743663600,"open":93.52,"high":95.36,"low":92.65,"close":93.52,"volume":362168},{"time":1743750000,"open":89.05,"high":92.46,"low":88.25,"close":89.05,"volume":498953},{"time":1744009200,"open":86.58,"high":88.53,"low":82.7,"close":86.58,"volume":835213},{"time":1744095600,"open":89.52,"high":91.0,"low":88.22,"close":89.52,"volume":351316},{"time":1744182000,"open":85.29,"high":86.56,"low":83.58,"close":85.29,"volume":243784},{"time":1744268400,"open":88.68,"high":93.7,"low":88.68,"close":88.68,"volume":594212},{"time":1744354800,"open":87.79,"high":88.97,"low":86.5,"close":87.79,"volume":169647},{"time":1744614000,"open":90.34,"high":91.29,"low":89.81,"close":90.34,"volume":203050},{"time":1744700400,"open":91.17,"high":91.64,"low":90.28,"close":91.17,"volume":174989},{"time":1744786800,"open":90.13,"high":90.49,"low":89.09,"close":90.13,"volume":97253},{"time":1744873200,"open":89.26,"high":89.95,"low":88.72,"close":89.26,"volume":95517},{"time":1745305200,"open":88.52,"high":88.63,"low":87.28,"close":88.52,"volume":147761},{"time":1745391600,"open":91.25,"high":92.35,"low":90.54,"close":91.25,"volume":123434},{"time":1745478000,"open":91.92,"high":92.1,"low":90.12,"close":91.92,"volume":123036},{"time":1745564400,"open":92.41,"high":93.05,"low":92.05,"close":92.41,"volume":42506},{"time":1745823600,"open":92.58,"high":93.49,"low":92.54,"close":92.58,"volume":93321},{"time":1745910000,"open":93.06,"high":93.4,"low":92.54,"close":93.06,"volume":112061},{"time":1745996400,"open":93.34,"high":93.74,"low":91.89,"close":93.34,"volume":174313},{"time":1746169200,"open":95.62,"high":95.79,"low":94.77,"close":95.62,"volume":147855},{"time":1746428400,"open":95.74,"high":95.86,"low":95.13,"close":95.74,"volume":101705},{"time":1746514800,"open":95.3,"high":95.48,"low":94.53,"close":95.3,"volume":88016},{"time":1746601200,"open":94.82,"high":95.26,"low":94.59,"close":94.82,"volume":96138},{"time":1746687600,"open":96.37,"high":96.53,"low":95.5,"close":96.37,"volume":122311},{"time":1746774000,"open":96.31,"high":96.96,"low":95.9,"close":96.31,"volume":86253},{"time":1747033200,"open":99.47,"high":100.1,"low":98.49,"close":99.47,"volume":108292},{"time":1747119600,"open":100.1,"high":100.38,"low":99.47,"close":100.1,"volume":87957},{"time":1747206000,"open":99.82,"high":100.11,"low":99.27,"close":99.82,"volume":92906},{"time":1747292400,"open":100.22,"high":100.22,"low":99.23,"close":100.22,"volume":111431},{"time":1747378800,"open":100.95,"high":100.95,"low":100.25,"close":100.95,"volume":105882},{"time":1747638000,"open":100.33,"high":100.42,"low":99.23,"close":100.33,"volume":68899},{"time":1747724400,"open":100.6,"high":100.93,"low":100.27,"close":100.6,"volume":53483},{"time":1747810800,"open":99.81,"high":99.89,"low":99.02,"close":99.81,"volume":62853},{"time":1747897200,"open":99.0,"high":99.12,"low":98.3,"close":99.0,"volume":83208},{"time":1747983600,"open":97.95,"high":98.99,"low":97.02,"close":97.95,"volume":87162},{"time":1748242800,"open":98.89,"high":99.04,"low":98.62,"close":98.89,"volume":50947},{"time":1748329200,"open":99.65,"high":99.65,"low":98.83,"close":99.65,"volume":71687},{"time":1748415600,"open":99.77,"high":100.2,"low":99.48,"close":99.77,"volume":69577},{"time":1748502000,"open":99.31,"high":101.29,"low":99.2,"close":99.31,"volume":86439},{"time":1748588400,"open":99.27,"high":99.76,"low":98.96,"close":99.27,"volume":78058},{"time":1748847600,"open":98.8,"high":99.1,"low":98.2,"close":98.8,"volume":68210},{"time":1748934000,"open":100.06,"high":100.06,"low":98.84,"close":100.06,"volume":63962},{"time":1749020400,"open":100.05,"high":100.44,"low":99.8,"close":100.05,"volume":57050},{"time":1749106800,"open":100.17,"high":100.44,"low":99.22,"close":100.17,"volume":64743},{"time":1749193200,"open":100.49,"high":100.9,"low":99.81,"close":100.49,"volume":59430},{"time":1749452400,"open":100.45,"high":100.75,"low":100.31,"close":100.45,"volume":52762},{"time":1749538800,"open":100.51,"high":100.77,"low":100.35,"close":100.51,"volume":38927},{"time":1749625200,"open":100.43,"high":100.9,"low":100.43,"close":100.43,"volume":72515},{"time":1749711600,"open":99.59,"high":99.8,"low":98.66,"close":99.59,"volume":352989},{"time":1749798000,"open":99.22,"high":99.61,"low":98.59,"close":99.22,"volume":210000},{"time":1750057200,"open":99.6,"high":99.7,"low":99.01,"close":99.6,"volume":66074},{"time":1750143600,"open":99.38,"high":99.59,"low":98.88,"close":99.38,"volume":244907},{"time":1750230000,"open":99.33,"high":99.68,"low":99.15,"close":99.33,"volume":65445},{"time":1750316400,"open":98.57,"high":99.17,"low":98.45,"close":98.57,"volume":64761},{"time":1750402800,"open":98.83,"high":99.42,"low":98.57,"close":98.83,"volume":42474},{"time":1750662000,"open":98.65,"high":99.19,"low":98.44,"close":98.65,"volume":98680},{"time":1750748400,"open":99.57,"high":99.81,"low":99.31,"close":99.57,"volume":57530},{"time":1750834800,"open":99.46,"high":99.98,"low":99.46,"close":99.46,"volume":37322},{"time":1750921200,"open":99.52,"high":99.67,"low":99.13,"close":99.52,"volume":76538},{"time":1751007600,"open":100.37,"high":100.37,"low":99.75,"close":100.37,"volume":51939},{"time":1751266800,"open":100.15,"high":100.54,"low":100.07,"close":100.15,"volume":85940},{"time":1751353200,"open":100.0,"high":100.21,"low":99.53,"close":100.0,"volume":103283},{"time":1751439600,"open":100.23,"high":100.41,"low":99.9,"close":100.23,"volume":97888},{"time":1751526000,"open":101.23,"high":101.29,"low":100.31,"close":101.23,"volume":79621},{"time":1751612400,"open":100.57,"high":100.78,"low":100.4,"close":100.57,"volume":70790},{"time":1751871600,"open":100.88,"high":101.26,"low":100.69,"close":100.88,"volume":97118},{"time":1751958000,"open":100.88,"high":101.12,"low":100.64,"close":100.88,"volume":64601},{"time":1752044400,"open":101.22,"high":101.59,"low":100.72,"close":101.22,"volume":101526},{"time":1752130800,"open":101.96,"high":101.96,"low":101.16,"close":101.96,"volume":68715},{"time":1752217200,"open":101.32,"high":101.69,"low":101.04,"close":101.32,"volume":70255},{"time":1752476400,"open":101.46,"high":101.49,"low":100.92,"close":101.46,"volume":59296},{"time":1752562800,"open":102.06,"high":102.18,"low":101.8,"close":102.06,"volume":133104},{"time":1752649200,"open":100.59,"high":102.15,"low":100.59,"close":100.59,"volume":78955},{"time":1752735600,"open":102.52,"high":102.57,"low":102.07,"close":102.52,"volume":71146},{"time":1752822000,"open":102.22,"high":102.71,"low":102.13,"close":102.22,"volume":69195},{"time":1753081200,"open":102.33,"high":102.58,"low":102.18,"close":102.33,"volume":42488},{"time":1753167600,"open":101.63,"high":102.17,"low":101.56,"close":101.63,"volume":49050},{"time":1753254000,"open":102.52,"high":102.64,"low":102.22,"close":102.52,"volume":84947},{"time":1753340400,"open":102.74,"high":102.99,"low":102.52,"close":102.74,"volume":52697},{"time":1753426800,"open":102.95,"high":103.02,"low":102.59,"close":102.95,"volume":72231},{"time":1753686000,"open":103.82,"high":103.92,"low":103.57,"close":103.82,"volume":102679},{"time":1753772400,"open":104.25,"high":104.82,"low":104.2,"close":104.25,"volume":78653},{"time":1753858800,"open":104.71,"high":104.95,"low":104.07,"close":104.71,"volume":84412},{"time":1753945200,"open":104.93,"high":105.85,"low":104.71,"close":104.93,"volume":162115},{"time":1754031600,"open":101.85,"high":104.01,"low":101.26,"close":101.85,"volume":176773},{"time":1754290800,"open":103.01,"high":103.07,"low":102.12,"close":103.01,"volume":121579},{"time":1754377200,"open":102.78,"high":103.82,"low":102.78,"close":102.78,"volume":50999},{"time":1754463600,"open":103.04,"high":103.41,"low":102.52,"close":103.04,"volume":60229},{"time":1754550000,"open":103.26,"high":103.9,"low":103.06,"close":103.26,"volume":65568},{"time":1754636400,"open":103.57,"high":103.84,"low":103.35,"close":103.57,"volume":99756},{"time":1754895600,"open":104.18,"high":104.27,"low":103.8,"close":104.18,"volume":71929},{"time":1754982000,"open":104.2,"high":104.41,"low":103.79,"close":104.2,"volume":57425},{"time":1755068400,"open":104.34,"high":104.77,"low":104.3,"close":104.34,"volume":44682},{"time":1755154800,"open":104.84,"high":105.03,"low":104.4,"close":104.84,"volume":55136},{"time":1755500400,"open":104.75,"high":104.96,"low":104.45,"close":104.75,"volume":89223},{"time":1755586800,"open":104.73,"high":105.03,"low":104.54,"close":104.73,"volume":35614},{"time":1755673200,"open":104.15,"high":104.6,"low":103.64,"close":104.15,"volume":39029},{"time":1755759600,"open":104.55,"high":104.61,"low":103.97,"close":104.55,"volume":44506},{"time":1755846000,"open":105.1,"high":105.23,"low":104.39,"close":105.1,"volume":78927},{"time":1756105200,"open":105.04,"high":105.06,"low":104.76,"close":105.04,"volume":39047},{"time":1756191600,"open":104.81,"high":104.98,"low":104.66,"close":104.81,"volume":45357},{"time":1756278000,"open":105.59,"high":105.77,"low":105.42,"close":105.59,"volume":55693},{"time":1756364400,"open":105.36,"high":105.82,"low":105.16,"close":105.36,"volume":84839},{"time":1756450800,"open":104.6,"high":105.51,"low":104.5,"close":104.6,"volume":53947},{"time":1756710000,"open":104.86,"high":104.86,"low":104.51,"close":104.86,"volume":65652},{"time":1756796400,"open":103.71,"high":104.77,"low":103.7,"close":103.71,"volume":119566},{"time":1756882800,"open":104.4,"high":104.78,"low":104.37,"close":104.4,"volume":37988},{"time":1756969200,"open":105.26,"high":105.34,"low":104.81,"close":105.26,"volume":59471},{"time":1757055600,"open":104.55,"high":105.73,"low":104.16,"close":104.55,"volume":73694},{"time":1757314800,"open":105.19,"high":105.26,"low":104.89,"close":105.19,"volume":138943},{"time":1757401200,"open":105.22,"high":105.32,"low":104.97,"close":105.22,"volume":60739},{"time":1757487600,"open":105.79,"high":106.2,"low":105.75,"close":105.79,"volume":82067},{"time":1757574000,"open":106.47,"high":106.47,"low":105.86,"close":106.47,"volume":55796},{"time":1757660400,"open":106.51,"high":106.68,"low":106.2,"close":106.51,"volume":57553},{"time":1757919600,"open":106.63,"high":106.77,"low":106.35,"close":106.63,"volume":82923},{"time":1758006000,"open":105.76,"high":106.69,"low":105.7,"close":105.76,"volume":78094},{"time":1758092400,"open":105.68,"high":105.89,"low":105.6,"close":105.68,"volume":63831},{"time":1758178800,"open":106.87,"high":107.02,"low":106.25,"close":106.87,"volume":97188},{"time":1758265200,"open":106.93,"high":107.18,"low":106.52,"close":106.93,"volume":83676},{"time":1758524400,"open":107.19,"high":107.26,"low":106.7,"close":107.19,"volume":70188},{"time":1758610800,"open":107.28,"high":107.54,"low":107.25,"close":107.28,"volume":105200},{"time":1758697200,"open":107.08,"high":107.42,"low":106.8,"close":107.08,"volume":62509},{"time":1758783600,"open":106.97,"high":107.05,"low":106.35,"close":106.97,"volume":80808},{"time":1758870000,"open":107.08,"high":107.48,"low":106.8,"close":107.08,"volume":52570},{"time":1759129200,"open":107.37,"high":107.76,"low":107.23,"close":107.37,"volume":201018},{"time":1759215600,"open":107.23,"high":107.42,"low":106.98,"close":107.23,"volume":67841},{"time":1759302000,"open":108.04,"high":108.74,"low":106.69,"close":108.04,"volume":118330},{"time":1759388400,"open":108.41,"high":108.62,"low":108.23,"close":108.41,"volume":172426},{"time":1759474800,"open":108.87,"high":108.98,"low":108.51,"close":108.87,"volume":86999},{"time":1759734000,"open":109.24,"high":109.61,"low":108.97,"close":109.24,"volume":123754},{"time":1759820400,"open":109.07,"high":109.7,"low":109.0,"close":109.07,"volume":132281},{"time":1759906800,"open":110.01,"high":110.05,"low":109.44,"close":110.01,"volume":89717},{"time":1759993200,"open":110.07,"high":110.24,"low":109.89,"close":110.07,"volume":103782},{"time":1760079600,"open":107.92,"high":110.34,"low":107.92,"close":107.92,"volume":119872},{"time":1760338800,"open":108.76,"high":108.76,"low":108.01,"close":108.76,"volume":382749},{"time":1760425200,"open":108.22,"high":108.33,"low":107.26,"close":108.22,"volume":231956},{"time":1760511600,"open":108.92,"high":109.5,"low":108.65,"close":108.92,"volume":188398},{"time":1760598000,"open":108.83,"high":109.13,"low":108.63,"close":108.83,"volume":81895},{"time":1760684400,"open":107.69,"high":108.4,"low":106.14,"close":107.69,"volume":284242},{"time":1760943600,"open":109.51,"high":109.63,"low":108.68,"close":109.51,"volume":101113},{"time":1761030000,"open":109.94,"high":110.09,"low":109.61,"close":109.94,"volume":158026},{"time":1761116400,"open":109.31,"high":110.19,"low":109.3,"close":109.31,"volume":105713},{"time":1761202800,"open":109.78,"high":109.87,"low":109.3,"close":109.78,"volume":127366},{"time":1761552000,"open":111.36,"high":111.4,"low":111.14,"close":111.36,"volume":146296},{"time":1761638400,"open":111.56,"high":111.85,"low":111.23,"close":111.56,"volume":208845},{"time":1761724800,"open":111.77,"high":112.14,"low":111.6,"close":111.77,"volume":98325},{"time":1761811200,"open":111.93,"high":112.07,"low":111.38,"close":111.93,"volume":298165},{"time":1761897600,"open":111.82,"high":112.24,"low":111.65,"close":111.82,"volume":308212},{"time":1762156800,"open":111.95,"high":112.55,"low":111.73,"close":111.95,"volume":282260},{"time":1762243200,"open":111.54,"high":111.85,"low":110.65,"close":111.54,"volume":210792},{"time":1762329600,"open":111.75,"high":111.75,"low":110.73,"close":111.75,"volume":240184},{"time":1762416000,"open":110.22,"high":111.56,"low":110.14,"close":110.22,"volume":173685},{"time":1762502400,"open":108.73,"high":110.52,"low":108.63,"close":108.73,"volume":210173},{"time":1762761600,"open":110.93,"high":111.33,"low":110.58,"close":110.93,"volume":275798},{"time":1762848000,"open":111.34,"high":111.64,"low":111.15,"close":111.34,"volume":205231},{"time":1762934400,"open":111.96,"high":112.46,"low":111.74,"close":111.96,"volume":131857},{"time":1763020800,"open":110.52,"high":112.06,"low":110.38,"close":110.52,"volume":181853},{"time":1763107200,"open":110.23,"high":110.35,"low":108.52,"close":110.23,"volume":296037},{"time":1763366400,"open":109.77,"high":110.6,"low":109.35,"close":109.77,"volume":515276},{"time":1763452800,"open":108.29,"high":108.75,"low":107.46,"close":108.29,"volume":341382},{"time":1763539200,"open":108.58,"high":109.32,"low":108.04,"close":108.58,"volume":139062},{"time":1763625600,"open":109.26,"high":110.66,"low":109.26,"close":109.26,"volume":179256},{"time":1763712000,"open":108.13,"high":108.14,"low":106.96,"close":108.13,"volume":320304},{"time":1763971200,"open":109.55,"high":109.68,"low":108.33,"close":109.55,"volume":153454},{"time":1764057600,"open":109.79,"high":109.79,"low":108.79,"close":109.79,"volume":147315},{"time":1764144000,"open":111.09,"high":111.13,"low":110.43,"close":111.09,"volume":93145},{"time":1764230400,"open":111.01,"high":111.19,"low":110.96,"close":111.01,"volume":58231},{"time":1764316800,"open":111.43,"high":111.63,"low":111.23,"close":111.43,"volume":48028},{"time":1764576000,"open":111.0,"high":111.06,"low":110.34,"close":111.0,"volume":161358},{"time":1764662400,"open":111.04,"high":111.52,"low":110.77,"close":111.04,"volume":127896},{"time":1764748800,"open":111.03,"high":111.19,"low":110.47,"close":111.03,"volume":128578},{"time":1764835200,"open":111.31,"high":111.51,"low":111.05,"close":111.31,"volume":65949},{"time":1764921600,"open":111.7,"high":112.04,"low":111.39,"close":111.7,"volume":67506},{"time":1765180800,"open":111.51,"high":111.81,"low":111.39,"close":111.51,"volume":92216},{"time":1765267200,"open":111.62,"high":111.73,"low":111.25,"close":111.62,"volume":167619},{"time":1765353600,"open":111.37,"high":111.47,"low":111.09,"close":111.37,"volume":80490},{"time":1765440000,"open":110.96,"high":111.23,"low":110.58,"close":110.96,"volume":230422},{"time":1765526400,"open":110.34,"high":111.79,"low":110.2,"close":110.34,"volume":189376},{"time":1765785600,"open":110.48,"high":111.17,"low":110.14,"close":110.48,"volume":158465},{"time":1765872000,"open":109.74,"high":110.21,"low":109.43,"close":109.74,"volume":275153},{"time":1765958400,"open":109.25,"high":110.66,"low":109.22,"close":109.25,"volume":127232},{"time":1766044800,"open":110.43,"high":110.5,"low":109.26,"close":110.43,"volume":156816},{"time":1766131200,"open":110.95,"high":110.98,"low":110.05,"close":110.95,"volume":165589},{"time":1766390400,"open":111.18,"high":111.22,"low":110.84,"close":111.18,"volume":71595},{"time":1766476800,"open":111.4,"high":111.47,"low":110.93,"close":111.4,"volume":64077},{"time":1766995200,"open":111.54,"high":111.8,"low":111.29,"close":111.54,"volume":91453},{"time":1767081600,"open":111.81,"high":111.88,"low":111.52,"close":111.81,"volume":104314},{"time":1767340800,"open":111.35,"high":112.08,"low":111.08,"close":111.35,"volume":128356},{"time":1767600000,"open":112.71,"high":112.85,"low":112.15,"close":112.71,"volume":177222},{"time":1767686400,"open":113.12,"high":113.34,"low":112.45,"close":113.12,"volume":208362},{"time":1767772800,"open":113.46,"high":113.55,"low":113.21,"close":113.46,"volume":120803},{"time":1767859200,"open":113.28,"high":113.33,"low":112.88,"close":113.28,"volume":144971},{"time":1767945600,"open":114.2,"high":114.35,"low":113.4,"close":114.2,"volume":94951},{"time":1768204800,"open":114.18,"high":114.2,"low":113.26,"close":114.18,"volume":92820},{"time":1768291200,"open":114.32,"high":114.58,"low":113.98,"close":114.32,"volume":100384},{"time":1768377600,"open":113.68,"high":114.34,"low":113.4,"close":113.68,"volume":173454},{"time":1768464000,"open":114.95,"high":115.08,"low":114.26,"close":114.95,"volume":122331},{"time":1768550400,"open":114.78,"high":114.97,"low":114.35,"close":114.78,"volume":117265},{"time":1768809600,"open":113.12,"high":113.64,"low":112.99,"close":113.12,"volume":109564},{"time":1768896000,"open":112.16,"high":112.28,"low":111.31,"close":112.16,"volume":193448},{"time":1768982400,"open":112.27,"high":112.58,"low":111.0,"close":112.27,"volume":116831},{"time":1769068800,"open":113.02,"high":113.49,"low":112.78,"close":113.02,"volume":125010},{"time":1769155200,"open":112.76,"high":113.1,"low":112.55,"close":112.76,"volume":100962},{"time":1769414400,"open":112.34,"high":112.57,"low":111.7,"close":112.34,"volume":201683},{"time":1769500800,"open":112.2,"high":112.9,"low":112.1,"close":112.2,"volume":115623},{"time":1769587200,"open":112.31,"high":112.55,"low":112.13,"close":112.31,"volume":270405},{"time":1769673600,"open":111.41,"high":112.77,"low":110.95,"close":111.41,"volume":104967},{"time":1769760000,"open":112.19,"high":112.5,"low":111.34,"close":112.19,"volume":307563},{"time":1770019200,"open":113.44,"high":113.5,"low":111.32,"close":113.44,"volume":200717},{"time":1770105600,"open":112.95,"high":114.03,"low":112.87,"close":112.95,"volume":96014},{"time":1770192000,"open":112.7,"high":113.26,"low":112.53,"close":112.7,"volume":174285},{"time":1770278400,"open":111.52,"high":112.64,"low":110.94,"close":111.52,"volume":330286},{"time":1770364800,"open":112.63,"high":112.68,"low":111.0,"close":112.63,"volume":194238},{"time":1770624000,"open":113.24,"high":113.25,"low":112.09,"close":113.24,"volume":114936},{"time":1770710400,"open":113.44,"high":113.71,"low":113.1,"close":113.44,"volume":82279},{"time":1770796800,"open":113.45,"high":114.24,"low":112.99,"close":113.45,"volume":126847},{"time":1770883200,"open":112.38,"high":113.9,"low":112.23,"close":112.38,"volume":132713},{"time":1770969600,"open":112.28,"high":112.46,"low":111.37,"close":112.28,"volume":242973},{"time":1771228800,"open":112.04,"high":112.47,"low":111.9,"close":112.04,"volume":81306},{"time":1771315200,"open":112.28,"high":112.47,"low":111.55,"close":112.28,"volume":233531},{"time":1771401600,"open":113.52,"high":113.57,"low":112.65,"close":113.52,"volume":64640},{"time":1771488000,"open":113.43,"high":113.63,"low":112.97,"close":113.43,"volume":59773},{"time":1771574400,"open":113.71,"high":114.0,"low":112.94,"close":113.71,"volume":85294},{"time":1771833600,"open":112.92,"high":114.0,"low":112.61,"close":112.92,"volume":109719},{"time":1771920000,"open":113.4,"high":113.67,"low":112.7,"close":113.4,"volume":236471},{"time":1772006400,"open":114.22,"high":114.4,"low":113.73,"close":114.22,"volume":85599},{"time":1772092800,"open":114.04,"high":114.63,"low":113.45,"close":114.04,"volume":116356},{"time":1772179200,"open":113.58,"high":114.2,"low":113.0,"close":113.58,"volume":106600},{"time":1772438400,"open":113.89,"high":114.2,"low":112.44,"close":113.89,"volume":344921},{"time":1772524800,"open":112.62,"high":113.24,"low":111.77,"close":112.62,"volume":224468},{"time":1772611200,"open":113.87,"high":114.03,"low":112.76,"close":113.87,"volume":309603},{"time":1772697600,"open":113.25,"high":114.26,"low":113.1,"close":113.25,"volume":319548},{"time":1773043200,"open":111.52,"high":111.61,"low":110.22,"close":111.52,"volume":203540},{"time":1773129600,"open":113.01,"high":113.15,"low":112.13,"close":113.01,"volume":264441},{"time":1773216000,"open":112.61,"high":113.03,"low":112.25,"close":112.61,"volume":133942},{"time":1773302400,"open":112.03,"high":112.61,"low":111.63,"close":112.03,"volume":56199},{"time":1773388800,"open":111.89,"high":112.85,"low":111.48,"close":111.89,"volume":226398},{"time":1773648000,"open":112.16,"high":112.66,"low":111.62,"close":112.16,"volume":236968},{"time":1773734400,"open":112.41,"high":112.88,"low":111.7,"close":112.41,"volume":231183},{"time":1773820800,"open":111.7,"high":113.07,"low":111.59,"close":111.7,"volume":284471},{"time":1773907200,"open":109.85,"high":111.2,"low":109.72,"close":109.85,"volume":199476},{"time":1773993600,"open":108.74,"high":110.35,"low":108.74,"close":108.74,"volume":169707},{"time":1774252800,"open":109.15,"high":111.34,"low":107.23,"close":109.15,"volume":203451},{"time":1774339200,"open":109.25,"high":109.51,"low":108.36,"close":109.25,"volume":201307},{"time":1774425600,"open":110.15,"high":110.42,"low":109.6,"close":110.15,"volume":172972},{"time":1774512000,"open":108.99,"high":109.84,"low":108.98,"close":108.99,"volume":59798},{"time":1774598400,"open":107.5,"high":108.92,"low":107.32,"close":107.5,"volume":125074},{"time":1774854000,"open":108.23,"high":108.23,"low":107.21,"close":108.23,"volume":85759},{"time":1774940400,"open":108.12,"high":108.42,"low":107.63,"close":108.12,"volume":115756},{"time":1775026800,"open":110.34,"high":110.42,"low":109.64,"close":110.34,"volume":188589},{"time":1775113200,"open":110.38,"high":110.85,"low":108.7,"close":110.38,"volume":71973},{"time":1775545200,"open":109.74,"high":111.07,"low":109.42,"close":109.74,"volume":87209},{"time":1775631600,"open":112.54,"high":113.1,"low":112.22,"close":112.54,"volume":255409},{"time":1775718000,"open":112.7,"high":112.7,"low":112.17,"close":112.7,"volume":70972},{"time":1775804400,"open":112.99,"high":113.33,"low":112.89,"close":112.99,"volume":90272},{"time":1776063600,"open":112.96,"high":113.09,"low":112.17,"close":112.96,"volume":69338},{"time":1776150000,"open":114.16,"high":114.2,"low":113.32,"close":114.16,"volume":70727},{"time":1776236400,"open":114.65,"high":114.72,"low":114.28,"close":114.65,"volume":126028},{"time":1776322800,"open":115.32,"high":115.45,"low":114.98,"close":115.32,"volume":96505},{"time":1776409200,"open":116.68,"high":116.68,"low":115.29,"close":116.68,"volume":149154},{"time":1776668400,"open":116.21,"high":116.56,"low":115.9,"close":116.21,"volume":120903},{"time":1776754800,"open":116.1,"high":116.97,"low":115.96,"close":116.1,"volume":90931},{"time":1776841200,"open":116.56,"high":116.66,"low":116.11,"close":116.56,"volume":80512},{"time":1776927600,"open":116.98,"high":117.0,"low":116.25,"close":116.98,"volume":124841},{"time":1777014000,"open":116.75,"high":117.09,"low":116.36,"close":116.75,"volume":61583},{"time":1777273200,"open":116.62,"high":116.97,"low":116.53,"close":116.62,"volume":77116},{"time":1777359600,"open":116.27,"high":117.22,"low":116.27,"close":116.27,"volume":100021},{"time":1777446000,"open":116.34,"high":116.81,"low":116.21,"close":116.34,"volume":57585},{"time":1777532400,"open":117.07,"high":117.35,"low":116.36,"close":117.07,"volume":108589},{"time":1777878000,"open":117.45,"high":118.1,"low":117.2,"close":117.45,"volume":192373},{"time":1777964400,"open":118.21,"high":118.45,"low":117.8,"close":118.21,"volume":366807},{"time":1778050800,"open":119.58,"high":119.67,"low":118.7,"close":119.58,"volume":150196},{"time":1778137200,"open":119.63,"high":120.17,"low":119.5,"close":119.63,"volume":123695},{"time":1778223600,"open":119.51,"high":119.62,"low":119.29,"close":119.51,"volume":93500},{"time":1778482800,"open":119.94,"high":119.95,"low":119.34,"close":119.94,"volume":98323},{"time":1778569200,"open":119.18,"high":119.75,"low":119.04,"close":119.18,"volume":84604},{"time":1778655600,"open":120.43,"high":120.63,"low":119.87,"close":120.43,"volume":152294},{"time":1778742000,"open":121.99,"high":122.06,"low":120.9,"close":121.99,"volume":86953},{"time":1778828400,"open":121.03,"high":121.51,"low":120.59,"close":121.03,"volume":142483},{"time":1779087600,"open":120.39,"high":121.0,"low":119.89,"close":120.39,"volume":125803},{"time":1779174000,"open":120.3,"high":121.02,"low":120.1,"close":120.3,"volume":109543}],"kama_v":[null,null,null,null,null,92.22,92.1636,91.9714,91.7448,91.3834,91.3802,91.3545,91.4437,91.6273,92.1545,92.6206,92.8756,93.1935,93.3714,93.5685,93.689,94.0679,94.3366,94.6803,94.6945,94.7437,94.7579,94.7617,94.7723,94.8742,94.8507,94.8482,94.8668,94.9108,94.9366,95.187,95.3928,95.6849,95.7281,95.8984,96.0184,96.1432,96.0702,95.8888,95.341,95.2273,95.2666,95.1093,94.924,94.8357,94.7423,94.5469,94.7288,94.6959,93.9891,92.6843,92.0681,91.7882,91.5944,91.5646,91.3937,91.6943,91.9635,92.8908,93.5171,93.7217,93.8774,94.0334,94.0835,94.0917,94.1609,94.2054,94.6695,94.7353,94.9806,94.9655,94.8653,94.3809,93.6327,93.4608,93.3944,93.3067,93.4089,93.9103,94.0332,94.2568,94.3423,94.6285,94.6753,94.8698,94.9999,95.2132,95.3163,95.9002,95.9782,96.0939,96.2854,96.3299,96.4835,96.8104,97.0034,97.3858,97.845,98.2546,98.8234,99.0265,99.1177,99.478,99.6268,99.6326,99.6536,99.6465,99.5725,99.5909,99.595,99.6034,99.5773,99.0418,98.9202,98.616,98.5112,98.7437,99.554,100.3267,101.7237,102.2291,102.6138,102.8261,102.7952,102.7252,102.6601,102.5916,102.6501,103.5409,103.8995,104.2212,104.1791,104.1998,104.2238,104.4201,104.5581,105.1228,105.3624,105.5275,105.5292,105.54,105.6351,105.6771,105.672,105.68,105.6677,105.6728,105.1985,105.0078,104.749,104.7184,104.5569,104.6796,104.7308,104.9405,104.9456,104.9635,104.9728,104.8571,104.5392,104.3009,104.3678,104.4731,105.2203,105.4322,105.6523,106.0016,106.2903,106.3156,106.1846,106.197,106.228,106.2659,106.4595,106.6121,106.6727,106.6819,106.834,106.8909,107.2055,107.3567,107.3736,107.3997,107.4174,107.4598,107.514,107.8946,107.8856,107.8844,107.5898,106.7635,106.7028,106.6931,106.4981,106.4406,105.81,104.0374,103.0467,101.7181,100.4394,98.8966,98.5887,98.0998,98.0722,98.0791,98.0485,98.1675,98.4815,98.569,99.1222,99.7451,99.8547,99.8658,99.688,98.652,98.6161,98.5742,97.1806,94.6858,92.0625,91.4912,89.8397,89.7239,89.6254,89.695,89.7865,89.8565,89.8257,89.7502,89.8461,89.9675,90.3254,90.9284,91.8758,92.5266,93.9014,94.7186,94.8933,94.8804,95.2286,95.3312,96.3645,97.6108,98.4291,99.0608,99.774,99.8378,99.9007,99.8976,99.7777,99.1356,99.1033,99.1486,99.1703,99.1775,99.1969,99.1801,99.2426,99.29,99.4317,99.649,99.9761,100.1548,100.2179,100.1216,99.7696,99.7397,99.6597,99.5873,99.3724,99.3251,99.1596,99.1803,99.1926,99.2689,99.5829,99.7354,99.7645,99.8502,100.2236,100.2411,100.3117,100.392,100.5177,100.6989,100.7798,100.8552,101.0621,101.0285,101.1134,101.2002,101.2872,101.305,101.5193,101.5838,101.7492,102.1353,103.0752,103.8018,104.3032,104.1008,104.0298,103.9016,103.7988,103.7346,103.6821,103.8219,103.9899,104.1455,104.4542,104.5616,104.6085,104.5902,104.5878,104.622,104.6523,104.6588,104.9179,104.9866,104.9519,104.9474,104.7962,104.7424,104.7621,104.7545,104.7759,104.8586,105.0242,105.2612,105.8162,106.1779,106.1411,106.1205,106.1736,106.2286,106.3106,106.6838,106.8076,106.8177,106.8377,106.8828,106.8981,107.1843,107.6077,108.0638,108.4922,108.694,109.1604,109.4709,109.3251,109.2931,109.2133,109.186,109.1493,109.0815,109.112,109.2324,109.2364,109.2804,109.893,110.2804,110.608,111.1956,111.4352,111.5825,111.581,111.5872,111.205,110.3746,110.4141,110.4505,110.5098,110.5102,110.48,110.3898,109.8077,109.3721,109.3565,109.1257,109.1432,109.2342,109.5886,109.7996,110.4763,110.5902,110.6808,110.6964,110.7536,110.8363,110.9749,111.1166,111.1421,111.1249,110.8431,110.7493,110.3813,109.9602,109.9927,110.0668,110.1599,110.4536,110.9365,111.3247,111.3274,111.6521,112.0157,112.3908,112.5637,113.1772,113.495,113.7404,113.737,113.9855,114.0606,113.9677,113.6717,113.5041,113.4112,113.283,113.1784,113.1418,113.1107,112.4812,112.4551,112.5754,112.6058,112.611,112.5693,112.5726,112.6016,112.6551,112.7261,112.6905,112.6612,112.4794,112.4253,112.4664,112.6601,112.937,112.935,112.9988,113.1237,113.2049,113.2207,113.3229,113.257,113.2896,113.2865,113.0386,113.0368,113.0226,112.889,112.7777,112.7259,112.6851,112.5211,111.8261,110.905,110.4325,110.077,110.0861,109.9906,109.7196,109.5997,109.4606,109.4951,109.5906,109.6239,110.479,111.1774,111.6465,111.9761,112.9279,113.6628,114.3756,115.3761,115.6356,115.745,115.9355,116.1635,116.1874,116.2342,116.2362,116.2438,116.2805,116.455,116.9267,118.106,118.7833,119.0656,119.4061,119.3778,119.4992,120.0252,120.1349,120.1477,120.1616],"kama_s":[null,null,null,null,null,null,null,null,null,null,null,null,null,null,null,null,null,null,null,null,null,94.6,94.6102,94.6539,94.6608,94.6856,94.7022,94.7151,94.7304,94.8072,94.7794,94.7827,94.8423,94.913,94.9779,95.0489,95.1238,95.2788,95.3482,95.487,95.5982,95.7181,95.7117,95.7061,95.679,95.6748,95.6749,95.6477,95.5988,95.5611,95.5211,95.5011,95.4997,95.4884,95.1329,94.4491,94.0185,93.8265,93.6194,93.475,93.3337,93.2782,93.2368,93.2469,93.2544,93.2589,93.2657,93.2793,93.286,93.2952,93.3039,93.3113,93.3419,93.3521,93.3848,93.4917,93.5051,93.4639,93.4351,93.4153,93.403,93.3871,93.4143,93.4723,93.4817,93.5007,93.5113,93.5638,93.587,93.6306,93.677,93.7219,93.7788,93.8188,93.8582,93.8885,93.9761,94.1187,94.3991,94.9119,95.2694,95.715,96.2323,96.6347,97.0996,97.5133,97.8076,98.3702,98.6838,98.9007,99.0794,99.1434,99.1818,99.2615,99.3131,99.3842,99.374,99.3503,99.3173,99.3069,99.2961,99.394,99.5201,99.701,99.9884,100.1519,100.3643,100.5599,100.5958,100.645,100.6972,100.751,100.9248,101.233,101.4646,101.7006,101.8095,101.9815,102.3572,102.8038,103.2941,103.7427,103.9722,104.1593,104.2513,104.3205,104.4766,104.5732,104.6142,104.7364,104.7947,104.8762,104.8539,104.8479,104.8341,104.8321,104.8185,104.8294,104.833,104.8479,104.85,104.8523,104.8564,104.8357,104.8089,104.7811,104.7853,104.7946,104.8112,104.8229,104.8341,104.8854,104.9368,105.0305,105.0316,105.0751,105.1228,105.2075,105.3255,105.3736,105.405,105.4405,105.5464,105.6276,105.8243,105.9818,106.0603,106.1318,106.1778,106.2247,106.2976,106.3887,106.4004,106.412,106.4133,106.4068,106.4067,106.4077,106.3896,106.3691,106.0959,105.6362,105.3016,104.466,103.6131,102.251,101.5323,100.8249,100.4292,100.1767,99.8657,99.7565,99.6947,99.622,99.692,99.7506,99.7748,99.7883,99.5981,99.3682,99.3031,99.2678,98.869,97.7168,96.3555,95.9233,95.0866,94.7716,94.4189,94.2679,94.1625,94.0118,93.7716,93.4674,93.3925,93.3313,93.2955,93.2703,93.264,93.2655,93.2838,93.313,93.3389,93.3505,93.4878,93.7085,94.1692,95.3093,95.9881,96.7857,97.4897,97.8728,98.3673,98.6343,98.7008,98.6237,98.652,98.762,98.8724,98.9109,98.9406,98.935,98.9968,99.0661,99.1566,99.2406,99.3176,99.3365,99.3444,99.3459,99.344,99.3496,99.35,99.3496,99.333,99.33,99.3204,99.3239,99.3247,99.3262,99.3499,99.3644,99.3815,99.387,99.436,99.4463,99.4592,99.4729,99.4972,99.5692,99.631,99.7266,99.861,99.8752,100.0158,100.1675,100.3101,100.3745,100.478,100.6033,100.7395,100.9193,101.1644,101.4752,101.7773,101.7779,101.8109,101.8305,101.8582,101.8885,101.9176,101.9942,102.0655,102.1265,102.3147,102.3992,102.4972,102.5407,102.6429,102.7527,102.8418,102.8999,102.9754,103.0159,103.0239,103.0325,103.0584,103.0962,103.2165,103.2522,103.319,103.3748,103.4438,103.5675,103.6822,103.7762,103.8067,103.8337,103.9738,104.0923,104.2007,104.3184,104.4262,104.4843,104.5626,104.7376,104.8638,105.2974,105.6961,106.0676,106.6862,107.0625,107.603,108.0215,108.0188,108.0498,108.0541,108.1108,108.1576,108.1515,108.2046,108.2772,108.3047,108.3598,108.5501,108.745,108.9374,109.147,109.2932,109.4289,109.5025,109.5761,109.5842,109.5727,109.5849,109.6545,109.7398,109.7576,109.7639,109.7639,109.7528,109.7405,109.7365,109.7169,109.716,109.7172,109.7264,109.7375,109.7492,109.7603,109.7725,109.7812,109.7912,109.8203,109.8787,109.8961,109.9025,109.9172,109.9195,109.923,109.9222,109.9118,109.9268,109.9538,110.0355,110.0895,110.1436,110.1697,110.1796,110.2407,110.3743,110.5387,110.6669,110.8813,111.0511,111.2545,111.3445,111.5996,111.8569,111.9126,111.9179,111.9313,112.0018,112.0297,112.0358,112.0383,112.0419,112.0387,112.0397,112.0769,112.082,112.0866,112.0726,112.0775,112.0911,112.104,112.1185,112.1224,112.1283,112.1249,112.1268,112.1525,112.1727,112.1888,112.1927,112.21,112.264,112.3035,112.3424,112.3792,112.382,112.4,112.4071,112.4034,112.4074,112.4091,112.4031,112.394,112.3927,112.3928,112.3884,112.3228,112.0892,111.9312,111.7755,111.7266,111.5814,111.1965,110.9841,110.7915,110.7772,110.7693,110.7233,110.737,110.7587,110.7682,110.7814,110.8493,110.9496,111.0821,111.3145,111.5376,111.9286,112.5348,113.1173,113.555,113.8701,114.1968,114.6796,115.218,115.7507,116.2858,117.0663,117.8133,118.2217,118.6432,118.7363,119.0723,119.6682,119.8531,119.9036,119.9297],"sar":[92.51,92.15,92.51,92.08,92.87,92.87,92.8517,92.8337,92.7871,92.7111,92.5851,92.4666,92.3552,90.61,90.6426,90.7205,90.8447,90.9632,91.1454,91.3618,91.6289,91.9136,92.2516,92.6105,93.0124,93.354,93.6444,93.8913,94.1452,94.3572,95.64,95.64,95.5992,95.5596,95.55,94.28,94.301,94.3472,94.4238,94.5484,94.6655,94.8053,94.9722,96.66,96.6338,96.5649,96.4982,96.4334,96.3203,96.1043,95.9013,95.7104,95.531,92.72,95.84,95.84,95.5541,95.2768,95.0078,94.7468,94.4937,94.2482,94.0101,86.31,86.4318,86.5518,86.7974,87.0357,87.3855,87.7196,88.1487,88.5519,89.0325,89.6236,90.1615,90.7483,91.3605,91.8992,95.85,95.7865,95.7241,95.6625,95.6019,95.5421,95.4833,95.4253,95.3683,91.62,91.6887,91.7564,91.823,91.9597,92.0923,92.3186,92.5347,92.741,93.0169,93.2763,93.5201,93.8479,94.151,94.4315,94.7769,95.171,95.6233,96.1817,96.759,97.2496,97.8272,98.3095,98.7121,99.0484,99.3292,100.75,100.7278,100.7059,100.6844,100.6369,100.4899,100.3495,100.1635,97.25,97.3196,97.3882,97.5373,97.8128,98.076,98.3272,98.6766,99.005,99.3137,99.6039,99.8767,100.1331,100.5056,100.9254,101.3074,101.655,101.9714,102.2592,102.631,102.9638,103.3761,103.739,104.0583,104.3393,104.5866,104.8042,105.0237,105.2135,106.43,106.4108,106.3919,106.3051,106.1083,105.9202,105.7407,105.5692,105.4054,101.93,101.9887,102.0464,102.1033,102.1594,102.2146,102.269,102.3225,102.3753,102.4912,102.6878,102.8756,103.0549,103.3024,103.6457,103.9633,103.98,103.98,104.2725,104.5431,104.8947,105.2147,105.5058,105.7708,106.0119,106.2314,106.4864,106.7146,106.9189,107.1017,107.2653,107.4118,107.5939,108.95,108.95,108.9303,108.8442,108.6658,108.4955,108.3328,108.1178,107.9157,107.4736,106.8675,106.1706,105.3173,104.347,103.1055,102.0502,101.1531,100.3907,99.7426,99.1917,96.07,96.128,96.1852,96.3237,96.5377,96.821,97.0874,101.26,101.1834,101.1079,101.0335,100.782,100.218,99.167,98.1789,97.2502,96.3772,95.5566,94.7852,94.0601,93.3785,92.7377,82.7,82.8447,82.9873,83.2892,83.7482,84.1866,84.7598,85.5871,86.5116,87.353,88.1186,89.0018,89.9568,91.3261,92.6842,93.8386,94.8198,95.8313,96.6759,97.3811,97.97,100.95,100.891,100.833,100.7758,97.02,97.084,97.1471,97.2093,97.2705,97.3308,97.3902,97.4487,97.5063,97.563,97.6189,97.674,97.7283,97.7817,97.8343,97.8861,97.9372,97.9875,98.037,98.0858,98.1339,98.1812,98.2279,98.2738,98.319,98.3636,98.4075,98.4507,98.4933,98.5353,98.6269,98.7769,98.9201,99.0569,99.2443,99.4205,99.6567,99.9315,100.1815,100.4091,100.6162,100.8654,101.124,101.5014,101.9992,102.4861,105.85,105.85,105.7811,105.7133,105.6465,105.5807,105.5159,105.4521,105.3892,105.3273,105.2663,105.2062,105.147,105.0887,101.26,101.3196,101.3782,101.436,101.566,101.7574,101.9403,102.1148,102.2816,102.4408,102.5929,102.7381,102.8768,103.0092,103.2007,103.4459,103.7369,104.0554,104.3404,104.5955,104.8865,105.1961,105.5057,105.8413,106.1216,106.35,106.35,106.6038,107.76,108.74,106.69,106.7244,106.8109,106.9409,107.1275,107.3609,107.629,110.34,110.2938,110.2483,110.2035,110.0816,106.14,106.1992,106.319,106.4351,106.6585,106.97,107.3578,107.7164,108.1235,108.5883,109.0043,109.3766,112.55,112.4912,112.4333,108.63,108.6874,112.46,112.4009,112.3427,112.1962,112.0541,111.9163,111.6933,111.4803,111.2769,106.96,107.0234,107.1616,107.2957,107.4257,107.5519,107.6742,107.8707,108.0583,108.2375,108.4086,108.572,108.728,108.8771,109.0194,109.1553,109.22,109.26,109.3851,109.5046,109.6187,109.7276,109.8688,110.0924,110.3846,110.717,111.0145,111.4147,111.767,112.1467,112.4752,112.8659,115.08,115.0487,114.9365,114.7593,114.5902,114.4286,114.2743,114.127,113.9863,113.8041,113.6329,110.95,110.9962,114.03,113.9836,113.938,113.893,110.94,110.9895,111.0383,111.0863,111.1336,111.1802,111.2261,111.2713,111.3158,111.3597,111.4029,111.4928,111.634,111.7688,114.63,114.5871,114.5448,114.5032,114.3747,114.2501,114.1292,114.0119,113.8981,113.7878,113.6808,113.5769,113.4034,113.1236,112.6816,112.2727,111.8945,111.5447,111.2211,110.8601,110.5316,107.21,107.2646,107.3788,107.6362,107.8821,108.209,108.5162,108.9425,109.4625,110.0912,110.8818,111.5776,112.3056,112.9353,113.545,114.1299,114.6183,115.0866,115.4706,115.8371,116.2897,116.7218,117.3114,117.8831,118.3405,118.7064,118.9991,119.04,119.644,122.06,122.0274],"sar_trend":[1,-1,-1,1,-1,-1,-1,-1,-1,-1,-1,-1,-1,1,1,1,1,1,1,1,1,1,1,1,1,1,1,1,1,1,-1,-1,-1,-1,-1,1,1,1,1,1,1,1,1,-1,-1,-1,-1,-1,-1,-1,-1,-1,-1,1,-1,-1,-1,-1,-1,-1,-1,-1,-1,1,1,1,1,1,1,1,1,1,1,1,1,1,1,1,-1,-1,-1,-1,-1,-1,-1,-1,-1,1,1,1,1,1,1,1,1,1,1,1,1,1,1,1,1,1,1,1,1,1,1,1,1,1,1,-1,-1,-1,-1,-1,-1,-1,-1,1,1,1,1,1,1,1,1,1,1,1,1,1,1,1,1,1,1,1,1,1,1,1,1,1,1,1,1,1,-1,-1,-1,-1,-1,-1,-1,-1,-1,1,1,1,1,1,1,1,1,1,1,1,1,1,1,1,1,1,1,1,1,1,1,1,1,1,1,1,1,1,1,1,1,1,-1,-1,-1,-1,-1,-1,-1,-1,-1,-1,-1,-1,-1,-1,-1,-1,-1,-1,-1,-1,1,1,1,1,1,1,1,-1,-1,-1,-1,-1,-1,-1,-1,-1,-1,-1,-1,-1,-1,-1,1,1,1,1,1,1,1,1,1,1,1,1,1,1,1,1,1,1,1,1,1,-1,-1,-1,-1,1,1,1,1,1,1,1,1,1,1,1,1,1,1,1,1,1,1,1,1,1,1,1,1,1,1,1,1,1,1,1,1,1,1,1,1,1,1,1,1,1,1,1,1,1,1,-1,-1,-1,-1,-1,-1,-1,-1,-1,-1,-1,-1,-1,-1,1,1,1,1,1,1,1,1,1,1,1,1,1,1,1,1,1,1,1,1,1,1,1,1,1,1,1,1,-1,-1,1,1,1,1,1,1,1,-1,-1,-1,-1,-1,1,1,1,1,1,1,1,1,1,1,1,1,-1,-1,-1,1,1,-1,-1,-1,-1,-1,-1,-1,-1,-1,1,1,1,1,1,1,1,1,1,1,1,1,1,1,1,1,1,1,1,1,1,1,1,1,1,1,1,1,1,1,1,1,-1,-1,-1,-1,-1,-1,-1,-1,-1,-1,-1,1,1,-1,-1,-1,-1,1,1,1,1,1,1,1,1,1,1,1,1,1,1,-1,-1,-1,-1,-1,-1,-1,-1,-1,-1,-1,-1,-1,-1,-1,-1,-1,-1,-1,-1,-1,1,1,1,1,1,1,1,1,1,1,1,1,1,1,1,1,1,1,1,1,1,1,1,1,1,1,1,1,1,-1,-1],"ao":[0.0,-0.02217889513288185,-0.014403049897168785,0.022159190496282122,-0.06608838594596023,-0.08897706946989103,-0.10967701640521454,-0.22785554692048038,-0.3583121048388165,-0.5100517498745205,-0.4644595535864795,-0.4911556791592204,-0.3853749048071933,-0.18356722402450032,-0.0015953828339405618,0.210036862023955,0.35765432173229783,0.5601101485022184,0.7058809684519503,0.8432348032983867,0.9398883327643262,1.091238516681642,1.2183544327767066,1.355445447838278,1.3722744026772062,1.3491427689775577,1.315440179028812,1.347066042709102,1.3154711654402291,1.3582297504285208,1.2205635436441469,1.0942055533741666,1.1184348277887892,1.1591268131455479,1.149164010327155,1.1671665718999975,1.1998657388503915,1.2338128917563296,1.3047994462915966,1.3054999757650307,1.3432733628275457,1.3479029204693518,1.242241586532927,1.0591352637120082,0.7775933011099738,0.6050015215416522,0.5630257076874727,0.35172859919573796,-0.032213071234394874,-0.23093306573518646,-0.22640806460263718,-0.22479482860676114,-0.07097884130168097,0.05037671230304852,-0.5173483469764761,-1.7165995367777782,-2.232511220761978,-2.343655457006136,-2.5102697235294897,-2.3405501856652506,-2.1369545263930263,-1.8775992460712132,-1.617231160935134,-1.0059752129887016,-0.5583943693331008,-0.17509295859386498,0.08881524981015332,0.32045256733981375,0.4430327557656284,0.5590642573476572,0.5906996657972456,0.6663453434282474,0.7787833579698287,0.904060124292684,1.0279478358453815,1.024690517362572,0.7068920198871922,0.4296358181098867,0.0644746354361132,-0.17056114565248492,-0.2687569736281432,-0.37196315064663565,-0.1599878979621394,0.0838012778447137,0.23764071876838955,0.4288536828695442,0.49622859227559957,0.7334969366287396,0.8377650153357052,0.9641370727564436,1.0773338677521167,1.102453621542054,1.274182765956752,1.360059284874211,1.3203571865996224,1.3814194150256611,1.3643647471925675,1.330885487969283,1.4183766434092178,1.5207326007154904,1.4961739653682287,1.5924337351485889,1.7245399518437523,1.8367141972037615,2.0508349127310765,2.2298437096829673,2.2483949319633467,2.426107742687975,2.480474077390795,2.4651618346894395,2.3651175294192512,2.286620646545231,2.1637317827069182,2.0362779006864145,1.9324890386655085,1.840167453958017,1.693630542000264,1.2736348356550877,0.9603713362401862,0.6441300528396283,0.43830031254084645,0.9798087771658288,1.3959858814605184,1.749411291763252,2.2481994817260613,2.5562606669038956,2.6835861594594803,2.8693221823476165,2.7108878765046853,2.497446500570234,2.2577991404460818,2.192044586912459,2.2260892973754807,2.4931837769592136,2.7062260627228056,2.758431777602226,2.71833468803635,2.6675403811398866,2.620513712393304,2.720502212732754,2.7880221498054,2.8875470874388185,2.8964241161075677,2.8227523804406047,2.7139389598988544,2.594364539091359,2.52674575554056,2.4833330712416455,2.346764734051078,2.1925590565513033,2.01072776148969,1.8852432471206413,1.4378619372711086,0.9399222813622856,0.7624157692449387,0.765823523244876,0.587578464390532,0.6257477329696997,0.6505495758520254,0.7754722039748856,0.8122330860625908,0.7851599006187229,0.7490132420387567,0.6346445583149176,0.4135610293991334,0.31977957382,0.34435848746937836,0.5863196188800401,0.8367950632398475,0.9961765548633963,1.1091161131291045,1.2666710954484728,1.4496682752955792,1.4773642302437793,1.066022595096527,1.054023103183198,1.1741586407196536,1.2548741182384902,1.4888101090905224,1.3735752013334661,1.2695724171111635,1.1422120060319685,1.3145111992558753,1.4127508887696365,1.5237531904939488,1.558300877430483,1.4852554183686948,1.4008129514695042,1.372195475716282,1.3882840519406443,1.4396143235205585,1.453417256100181,1.360450659046947,1.2328469134146474,0.8617504136787062,0.39319981981924457,0.1729289570239132,0.015660067797668376,-0.29056060970511055,-0.31587984466496266,-0.9059155081444317,-1.6139627743638414,-2.2265961415748023,-2.8719718386324473,-3.401102227570391,-4.135542764789008,-4.560139861739245,-4.7913885797033515,-4.832465550283331,-4.65458472790462,-4.469053477967648,-4.207477544668691,-3.810041850346039,-3.583533625198413,-3.0635947442119402,-2.544157774319487,-2.159782675963072,-2.032620503041045,-2.1296610390090933,-2.5699657980346586,-2.580397022201808,-2.598160367266317,-3.30067579433522,-4.454230914977245,-6.120470489493016,-6.440839794781297,-7.450946268732835,-6.878508248896054,-7.0417694344675965,-6.513729117192625,-5.968204506301674,-5.722823849641259,-5.555299662019721,-5.623617768737859,-4.9185192809451195,-4.414256326855053,-3.7168948195222242,-3.080984248179078,-2.5959687874804587,-2.2458016578641633,-1.490707705952616,-0.8939882718739085,-0.5537507133327466,-0.3206723541629941,0.05894269145133535,0.40657861182386057,1.1991339062167867,1.8639534431566176,2.2621263773797438,2.5181261388817546,2.8319305754111213,2.863915145865974,2.9950835771888507,2.8242299713814845,2.519388292226097,2.131865040396548,1.986483551712766,1.9343711331199671,1.9856003266509674,2.0715678734172798,1.9320871355718197,1.6689239527473063,1.6132737841438143,1.6800898005377007,1.6474082384140019,1.7020128603770672,1.750061512192957,1.76482337323867,1.770301002769088,1.4721349258829548,1.215186045172743,1.0653054563045572,0.9209564322454469,0.8404396107470973,0.6548172165539654,0.5498799709870497,0.4331053103011868,0.4880193541266209,0.5507375720367378,0.5255056696935156,0.6274423068762758,0.7378124042207759,0.7214265310050934,0.7544982764807457,0.8914983879944742,0.9351415235881149,1.0268947025510755,1.0587857193599888,1.1192469866976182,1.2241201404895463,1.2431859275193347,1.208050514547594,1.3173404571451215,1.256232951753347,1.3782894636252934,1.4641964246920338,1.4963141002192515,1.3983279227865495,1.4180263406905311,1.474376399930918,1.502804131827844,1.6827241540571976,1.9334499927222026,2.0831282644535634,2.3077132982543844,1.923453172447097,1.6165340044538539,1.5123688673210864,1.3524969988100395,1.3194446740978378,1.299400908576942,1.35152184653586,1.3816075256989109,1.4670375347544677,1.5412054209454311,1.569706508179678,1.5828653943104456,1.4413080673039218,1.3534027962331834,1.3721926885985454,1.3851624940859892,1.3571895271719825,1.467483330216595,1.5042635816268017,1.4152471619615454,1.2703677931684325,1.0629826739323818,0.9667184951071306,0.9812635401732734,0.9524607511428513,0.943557381328489,0.9372819769426002,1.0795256730394698,1.2013338193643364,1.323342941145313,1.4138585721089925,1.3872756292476254,1.2618736063823803,1.3268124352686783,1.395243316047825,1.4487733117917685,1.5459657951796544,1.5376452836433288,1.4307237330039584,1.4195336254229858,1.4598057664159825,1.4105363154668709,1.454866567221245,1.6023597105557315,1.7454818071932863,1.9268609108665231,2.0391662217518842,2.1656305695418325,2.2858348413671763,2.1578599567180134,1.8928592305911138,1.564639270108131,1.557045787343725,1.4918247793048494,1.113893044753965,1.1942639509778985,1.36807240508125,1.4511867443849127,1.4583721031146695,1.7675831059007407,2.0130597874981504,2.2215313471038485,2.309249985297683,2.380719115080396,2.4348555463332957,2.266710611219267,2.113498293504108,1.89974756094594,1.4755628549182234,1.420667999413638,1.4464111153233574,1.579916063080958,1.4820384121004508,1.0474029824476077,0.8292337768669853,0.3024681335305388,0.0365416024019396,0.09482917562556281,-0.3300943063677835,-0.34525278255441094,-0.29607555182042233,0.030286157237327416,0.3175310889558318,0.5845823296887147,0.6242881692313489,0.729268837349295,0.7323380412397427,0.8108322962543042,0.9386480157969146,0.9934438364006439,0.9967865870027879,0.9444100217029217,0.8215600430510221,0.7403074226967874,0.6067029342658259,0.3425227520946805,0.17395982794170095,0.04070492632823175,0.06835787322702913,0.1862564912285194,0.29975294664309615,0.4422649191555337,0.5666150583313083,0.6233119547432864,0.8319285218634604,1.04374346803462,1.2721528409717138,1.3624612769724251,1.5553585981848812,1.6415807784994882,1.7851730405824071,1.7821386762116305,1.9088201260139925,1.9692041660152881,1.7243797279375457,1.2334769337576006,0.8677536742317926,0.8561309593792146,0.775896353870678,0.5750028926488682,0.4951213703084676,0.4007034465053039,0.23564007517151708,0.12712209778916872,0.14306867894754305,0.35287295677626673,0.3891577378601738,0.19614981079735117,0.06650620365319071,0.13395061027514998,0.3214799782359705,0.4899972836103501,0.49609258547488366,0.2715297891528081,0.1609243316201372,0.046661700480072454,0.1773376641760933,0.3038534355953715,0.42176349315013795,0.4672959502385794,0.46967485876403714,0.6343626734956729,0.73693570289484,0.7140849570633208,0.6337252371171473,0.4106671752109037,0.4187100611980128,0.4733802145584036,-0.02797263377692616,-0.04942283317959095,-0.0638851479974818,-0.1734852282160233,-0.23983082769355235,-0.2881414769420587,-0.2892603063466197,-0.2782047261975009,-0.6270551495812953,-1.0412487662603667,-1.3694103748325261,-1.649404212691465,-1.6165160978351167,-1.6858804066552722,-1.9596327672204268,-2.2023624555305332,-2.283723948307099,-1.9219547415153215,-1.687854512113148,-1.4075569071558363,-0.723488325553518,-0.2728118653275118,0.17995724674742064,0.40498679649539326,0.7762580870037539,1.1704251363246385,1.5703300772531463,1.9791868012319753,2.2872826100343246,2.5177964409690077,2.629405940532905,2.717052161229603,2.759500949285197,2.75491858726852,2.711357731173507,2.5964987547789065,2.5447201603957694,2.6250732275157844,2.736000863143957,2.979784922307772,3.234964159531586,3.2959133761302013,3.328570559096775,3.255899294756219,3.3228902510501825,3.560006763988639,3.5938961426542306,3.4498409180985448,3.320868012774028],"signals":["NONE","NONE","NONE","NONE","NONE","NONE","NONE","NONE","NONE","NONE","NONE","NONE","NONE","NONE","NONE","NONE","NONE","NONE","NONE","NONE","NONE","NONE","NONE","NONE","NONE","NONE","NONE","NONE","NONE","NONE","NONE","NONE","NONE","NONE","NONE","NONE","NONE","NONE","NONE","NONE","BUY3","BUY3","NONE","NONE","NONE","NONE","NONE","NONE","NONE","NONE","NONE","NONE","NONE","NONE","NONE","NONE","NONE","NONE","NONE","NONE","NONE","NONE","NONE","WATCH","BUY1","BUY1","BUY3","BUY3","BUY3","WATCH","WATCH","BUY2","BUY3","BUY2","BUY3","WATCH","WATCH","NONE","NONE","NONE","NONE","NONE","NONE","NONE","NONE","NONE","NONE","BUY2","BUY3","BUY3","BUY3","BUY3","BUY2","BUY2","BUY1","BUY1","BUY1","BUY1","BUY1","BUY2","BUY1","BUY1","BUY2","BUY3","BUY3","BUY3","BUY3","BUY3","BUY3","WATCH","WATCH","WATCH","WATCH","NONE","NONE","NONE","NONE","NONE","NONE","NONE","NONE","WATCH","BUY1","BUY1","BUY2","BUY1","BUY2","BUY3","WATCH","WATCH","WATCH","WATCH","WATCH","BUY2","WATCH","BUY1","WATCH","WATCH","BUY1","BUY1","BUY2","BUY3","BUY3","BUY1","WATCH","WATCH","BUY1","BUY1","WATCH","WATCH","NONE","NONE","NONE","NONE","NONE","NONE","NONE","NONE","NONE","WATCH","WATCH","WATCH","WATCH","NONE","NONE","NONE","WATCH","WATCH","BUY1","WATCH","WATCH","BUY2","BUY2","BUY3","WATCH","WATCH","WATCH","WATCH","WATCH","WATCH","WATCH","WATCH","WATCH","WATCH","BUY3","BUY1","WATCH","WATCH","WATCH","WATCH","BUY1","BUY2","NONE","NONE","NONE","NONE","NONE","NONE","NONE","NONE","NONE","NONE","NONE","NONE","NONE","NONE","NONE","NONE","NONE","NONE","NONE","NONE","NONE","NONE","BUY1","BUY1","BUY1","BUY1","NONE","NONE","NONE","NONE","NONE","NONE","NONE","NONE","NONE","NONE","NONE","NONE","NONE","NONE","NONE","NONE","NONE","NONE","NONE","NONE","NONE","BUY1","BUY1","BUY1","BUY1","WATCH","WATCH","BUY2","BUY3","BUY3","BUY3","BUY3","BUY3","BUY3","BUY3","WATCH","WATCH","NONE","NONE","NONE","NONE","WATCH","WATCH","NONE","WATCH","WATCH","WATCH","BUY1","BUY2","BUY1","WATCH","WATCH","NONE","WATCH","WATCH","NONE","NONE","NONE","NONE","WATCH","WATCH","WATCH","BUY1","WATCH","WATCH","WATCH","BUY2","BUY2","BUY3","BUY2","BUY3","BUY3","WATCH","BUY1","BUY1","WATCH","WATCH","BUY1","WATCH","WATCH","WATCH","WATCH","WATCH","BUY1","BUY1","BUY3","BUY3","NONE","NONE","NONE","NONE","NONE","NONE","NONE","NONE","NONE","NONE","NONE","NONE","NONE","NONE","WATCH","BUY2","WATCH","WATCH","BUY1","WATCH","WATCH","WATCH","WATCH","WATCH","WATCH","WATCH","WATCH","WATCH","WATCH","BUY1","BUY1","WATCH","WATCH","WATCH","BUY2","BUY3","BUY3","BUY1","WATCH","WATCH","WATCH","BUY1","NONE","NONE","BUY3","BUY3","BUY3","BUY3","BUY3","NONE","WATCH","NONE","NONE","NONE","NONE","NONE","WATCH","WATCH","WATCH","BUY2","BUY2","BUY3","BUY2","BUY2","BUY3","WATCH","WATCH","WATCH","NONE","NONE","NONE","WATCH","WATCH","NONE","NONE","NONE","NONE","NONE","NONE","NONE","NONE","NONE","WATCH","WATCH","WATCH","BUY3","BUY2","BUY2","BUY3","BUY3","BUY3","WATCH","WATCH","WATCH","WATCH","NONE","NONE","WATCH","WATCH","WATCH","WATCH","WATCH","WATCH","WATCH","WATCH","BUY2","BUY3","BUY3","BUY3","BUY3","BUY3","WATCH","WATCH","BUY2","NONE","NONE","NONE","NONE","NONE","NONE","NONE","NONE","NONE","NONE","NONE","WATCH","WATCH","NONE","NONE","NONE","NONE","WATCH","WATCH","WATCH","NONE","WATCH","WATCH","BUY2","BUY1","WATCH","WATCH","WATCH","BUY2","BUY1","BUY1","NONE","NONE","NONE","NONE","NONE","NONE","NONE","NONE","NONE","NONE","NONE","NONE","NONE","NONE","NONE","NONE","NONE","NONE","NONE","NONE","NONE","NONE","NONE","BUY1","BUY1","BUY1","BUY3","BUY3","BUY3","BUY3","BUY3","BUY3","BUY3","BUY3","BUY3","BUY3","BUY1","WATCH","WATCH","WATCH","WATCH","BUY2","BUY3","BUY3","BUY3","BUY3","WATCH","WATCH","BUY2","BUY3","NONE","NONE"],"uscite":["","","","","","","","","","","","","","","","","","","","","","","","","","","","","","","","","","","","","","","","","","","USCITA","STOP","STOP","STOP","ATTENZIONE","STOP","STOP","STOP","STOP","STOP","STOP","USCITA","STOP","STOP","STOP","STOP","STOP","STOP","STOP","STOP","STOP","","","","","","","","","","","","","","","USCITA","STOP","STOP","STOP","STOP","ATTENZIONE","ATTENZIONE","ATTENZIONE","ATTENZIONE","ATTENZIONE","","","","","","","","","","","","","","","","","","","","","","","","","","","ATTENZIONE","ATTENZIONE","ATTENZIONE","STOP","STOP","STOP","STOP","STOP","","","","","","","","","","","","","","","","","","","","","","","","","","","","","","ATTENZIONE","ATTENZIONE","STOP","STOP","STOP","STOP","STOP","ATTENZIONE","ATTENZIONE","","","","","USCITA","USCITA","USCITA","","","","","","","","","","","","","","","","","","","","","","","","","","","ATTENZIONE","ATTENZIONE","ATTENZIONE","STOP","STOP","ATTENZIONE","STOP","STOP","STOP","STOP","STOP","STOP","STOP","STOP","STOP","STOP","STOP","STOP","STOP","STOP","USCITA","USCITA","","","","","USCITA","STOP","STOP","STOP","STOP","STOP","STOP","STOP","STOP","STOP","STOP","STOP","STOP","STOP","STOP","STOP","USCITA","USCITA","USCITA","USCITA","USCITA","","","","","","","","","","","","","","","","","STOP","ATTENZIONE","ATTENZIONE","ATTENZIONE","","","USCITA","","","","","","","","","USCITA","","","USCITA","USCITA","USCITA","USCITA","","","","","","","","","","","","","","","","","","","","","","","","","","","","","ATTENZIONE","ATTENZIONE","ATTENZIONE","ATTENZIONE","ATTENZIONE","ATTENZIONE","ATTENZIONE","ATTENZIONE","ATTENZIONE","ATTENZIONE","ATTENZIONE","ATTENZIONE","ATTENZIONE","ATTENZIONE","","","","","","","","","","","","","","","","","","","","","","","","","","","","","ATTENZIONE","ATTENZIONE","","","","","","USCITA","","ATTENZIONE","ATTENZIONE","ATTENZIONE","STOP","ATTENZIONE","","","","","","","","","","","","","STOP","ATTENZIONE","ATTENZIONE","","","ATTENZIONE","ATTENZIONE","STOP","STOP","STOP","STOP","STOP","ATTENZIONE","ATTENZIONE","","","","","","","","","","","","","","USCITA","USCITA","","","","","","","","","","","","","","","","","","ATTENZIONE","ATTENZIONE","ATTENZIONE","ATTENZIONE","ATTENZIONE","ATTENZIONE","ATTENZIONE","ATTENZIONE","STOP","ATTENZIONE","ATTENZIONE","","","STOP","ATTENZIONE","ATTENZIONE","ATTENZIONE","","","","USCITA","","","","","","","","","","","ATTENZIONE","ATTENZIONE","ATTENZIONE","STOP","ATTENZIONE","ATTENZIONE","STOP","STOP","STOP","ATTENZIONE","STOP","STOP","STOP","STOP","STOP","STOP","STOP","STOP","STOP","STOP","STOP","USCITA","USCITA","","","","","","","","","","","","","","","","","","","","","","","","","","","","ATTENZIONE","ATTENZIONE"],"perf":{"trades":19,"closed":18,"wins":5,"wr":27.8,"totalPnl":3.71,"best":8.39,"worst":-3.28,"avg":0.21,"dd":7.1},"trades":[{"entSig":"BUY3","exitSig":"STOP","entTime":1721026800,"exitTime":1721372400,"entPrice":96.34,"exitPrice":94.36,"pnlPct":-2.0552,"isOpen":false,"days":4},{"entSig":"WATCH","exitSig":"USCITA","entTime":1723791600,"exitTime":1725519600,"entPrice":94.05,"exitPrice":92.95,"pnlPct":-1.1696,"isOpen":false,"days":14},{"entSig":"BUY2","exitSig":"STOP","entTime":1726729200,"exitTime":1730275200,"entPrice":95.96,"exitPrice":99.28,"pnlPct":3.4598,"isOpen":false,"days":29},{"entSig":"WATCH","exitSig":"STOP","entTime":1730880000,"exitTime":1734595200,"entPrice":101.02,"exitPrice":103.99,"pnlPct":2.94,"isOpen":false,"days":31},{"entSig":"WATCH","exitSig":"USCITA","entTime":1736150400,"exitTime":1736496000,"entPrice":105.79,"exitPrice":104.12,"pnlPct":-1.5786,"isOpen":false,"days":4},{"entSig":"WATCH","exitSig":"STOP","entTime":1736928000,"exitTime":1740470400,"entPrice":105.45,"exitPrice":105.03,"pnlPct":-0.3983,"isOpen":false,"days":29},{"entSig":"BUY1","exitSig":"USCITA","entTime":1742803200,"exitTime":1743148800,"entPrice":100.7,"exitPrice":97.83,"pnlPct":-2.85,"isOpen":false,"days":4},{"entSig":"BUY1","exitSig":"STOP","entTime":1745996400,"exitTime":1747983600,"entPrice":93.34,"exitPrice":97.95,"pnlPct":4.9389,"isOpen":false,"days":16},{"entSig":"WATCH","exitSig":"USCITA","entTime":1748502000,"exitTime":1749798000,"entPrice":99.31,"exitPrice":99.22,"pnlPct":-0.0906,"isOpen":false,"days":11},{"entSig":"WATCH","exitSig":"USCITA","entTime":1750057200,"exitTime":1750402800,"entPrice":99.6,"exitPrice":98.83,"pnlPct":-0.7731,"isOpen":false,"days":4},{"entSig":"WATCH","exitSig":"USCITA","entTime":1750748400,"exitTime":1760079600,"entPrice":99.57,"exitPrice":107.92,"pnlPct":8.3861,"isOpen":false,"days":77},{"entSig":"WATCH","exitSig":"STOP","entTime":1760338800,"exitTime":1760684400,"entPrice":108.76,"exitPrice":107.69,"pnlPct":-0.9838,"isOpen":false,"days":4},{"entSig":"WATCH","exitSig":"STOP","entTime":1761030000,"exitTime":1762502400,"entPrice":109.94,"exitPrice":108.73,"pnlPct":-1.1006,"isOpen":false,"days":12},{"entSig":"WATCH","exitSig":"STOP","entTime":1762934400,"exitTime":1763452800,"entPrice":111.96,"exitPrice":108.29,"pnlPct":-3.278,"isOpen":false,"days":4},{"entSig":"WATCH","exitSig":"USCITA","entTime":1764230400,"exitTime":1765872000,"entPrice":111.01,"exitPrice":109.74,"pnlPct":-1.144,"isOpen":false,"days":13},{"entSig":"WATCH","exitSig":"STOP","entTime":1766044800,"exitTime":1769673600,"entPrice":110.43,"exitPrice":111.41,"pnlPct":0.8874,"isOpen":false,"days":25},{"entSig":"WATCH","exitSig":"USCITA","entTime":1770105600,"exitTime":1771228800,"entPrice":112.95,"exitPrice":112.04,"pnlPct":-0.8057,"isOpen":false,"days":9},{"entSig":"WATCH","exitSig":"STOP","entTime":1771315200,"exitTime":1773043200,"entPrice":112.28,"exitPrice":111.52,"pnlPct":-0.6769,"isOpen":false,"days":13},{"entSig":"BUY1","exitSig":"OPEN","entTime":1775631600,"exitTime":1779174000,"entPrice":112.54,"exitPrice":120.3,"pnlPct":6.8953,"isOpen":true,"days":28}]}