{"ticker":"XG12","name":"XG12","categoria":"Tematici","is_bond":false,"updated":"20/07/2026 10:20","bars":[{"time":1721631600,"open":28.31,"high":28.31,"low":28.31,"close":28.31,"volume":0},{"time":1721718000,"open":28.31,"high":28.31,"low":28.31,"close":28.31,"volume":0},{"time":1721804400,"open":28.31,"high":28.31,"low":28.31,"close":28.31,"volume":0},{"time":1721890800,"open":28.31,"high":28.31,"low":28.31,"close":28.31,"volume":0},{"time":1721977200,"open":28.31,"high":28.31,"low":28.31,"close":28.31,"volume":0},{"time":1722236400,"open":27.94,"high":27.895,"low":27.895,"close":27.94,"volume":290},{"time":1722322800,"open":27.94,"high":27.94,"low":27.94,"close":27.94,"volume":0},{"time":1722409200,"open":27.94,"high":27.94,"low":27.94,"close":27.94,"volume":0},{"time":1722495600,"open":27.955,"high":28.15,"low":27.955,"close":27.955,"volume":107},{"time":1722582000,"open":27.955,"high":27.955,"low":27.955,"close":27.955,"volume":0},{"time":1722841200,"open":27.955,"high":27.955,"low":27.955,"close":27.955,"volume":0},{"time":1722927600,"open":27.955,"high":27.955,"low":27.955,"close":27.955,"volume":0},{"time":1723014000,"open":27.955,"high":27.955,"low":27.955,"close":27.955,"volume":0},{"time":1723100400,"open":27.955,"high":27.955,"low":27.955,"close":27.955,"volume":0},{"time":1723186800,"open":26.77,"high":26.805,"low":26.805,"close":26.77,"volume":1},{"time":1723446000,"open":26.77,"high":26.77,"low":26.77,"close":26.77,"volume":0},{"time":1723532400,"open":26.77,"high":26.77,"low":26.77,"close":26.77,"volume":0},{"time":1723618800,"open":26.77,"high":26.77,"low":26.77,"close":26.77,"volume":0},{"time":1723791600,"open":26.77,"high":26.77,"low":26.77,"close":26.77,"volume":0},{"time":1724050800,"open":26.77,"high":26.77,"low":26.77,"close":26.77,"volume":0},{"time":1724137200,"open":27.135,"high":27.125,"low":27.125,"close":27.135,"volume":300},{"time":1724223600,"open":27.135,"high":27.135,"low":27.135,"close":27.135,"volume":0},{"time":1724310000,"open":27.135,"high":27.135,"low":27.135,"close":27.135,"volume":0},{"time":1724396400,"open":27.135,"high":27.135,"low":27.135,"close":27.135,"volume":0},{"time":1724655600,"open":27.135,"high":27.135,"low":27.135,"close":27.135,"volume":0},{"time":1724742000,"open":27.135,"high":27.135,"low":27.135,"close":27.135,"volume":0},{"time":1724828400,"open":27.135,"high":27.135,"low":27.135,"close":27.135,"volume":0},{"time":1724914800,"open":27.135,"high":27.135,"low":27.135,"close":27.135,"volume":0},{"time":1725001200,"open":27.895,"high":27.94,"low":27.94,"close":27.895,"volume":234},{"time":1725260400,"open":28.065,"high":28.065,"low":28.065,"close":28.065,"volume":1},{"time":1725346800,"open":28.065,"high":28.065,"low":28.065,"close":28.065,"volume":0},{"time":1725433200,"open":28.065,"high":28.065,"low":28.065,"close":28.065,"volume":0},{"time":1725519600,"open":28.065,"high":28.065,"low":28.065,"close":28.065,"volume":0},{"time":1725606000,"open":27.11,"high":27.34,"low":27.34,"close":27.11,"volume":300},{"time":1725865200,"open":27.11,"high":27.11,"low":27.11,"close":27.11,"volume":0},{"time":1725951600,"open":27.34,"high":27.315,"low":27.315,"close":27.34,"volume":1},{"time":1726038000,"open":27.655,"high":27.475,"low":27.475,"close":27.655,"volume":135},{"time":1726124400,"open":27.655,"high":27.655,"low":27.655,"close":27.655,"volume":0},{"time":1726210800,"open":27.655,"high":27.655,"low":27.655,"close":27.655,"volume":0},{"time":1726470000,"open":27.655,"high":27.655,"low":27.655,"close":27.655,"volume":0},{"time":1726556400,"open":27.655,"high":27.655,"low":27.655,"close":27.655,"volume":0},{"time":1726642800,"open":27.655,"high":27.655,"low":27.655,"close":27.655,"volume":0},{"time":1726729200,"open":27.655,"high":27.655,"low":27.655,"close":27.655,"volume":0},{"time":1726815600,"open":27.655,"high":27.655,"low":27.655,"close":27.655,"volume":0},{"time":1727074800,"open":27.655,"high":27.655,"low":27.655,"close":27.655,"volume":0},{"time":1727161200,"open":27.655,"high":27.655,"low":27.655,"close":27.655,"volume":0},{"time":1727247600,"open":27.655,"high":27.655,"low":27.655,"close":27.655,"volume":0},{"time":1727334000,"open":27.655,"high":27.655,"low":27.655,"close":27.655,"volume":0},{"time":1727420400,"open":27.655,"high":27.655,"low":27.655,"close":27.655,"volume":0},{"time":1727679600,"open":27.655,"high":27.655,"low":27.655,"close":27.655,"volume":0},{"time":1727766000,"open":27.655,"high":27.655,"low":27.655,"close":27.655,"volume":0},{"time":1727852400,"open":27.655,"high":27.655,"low":27.655,"close":27.655,"volume":0},{"time":1727938800,"open":27.655,"high":27.655,"low":27.655,"close":27.655,"volume":0},{"time":1728025200,"open":27.655,"high":27.655,"low":27.655,"close":27.655,"volume":0},{"time":1728284400,"open":27.655,"high":27.655,"low":27.655,"close":27.655,"volume":0},{"time":1728370800,"open":27.655,"high":27.655,"low":27.655,"close":27.655,"volume":0},{"time":1728457200,"open":27.655,"high":27.655,"low":27.655,"close":27.655,"volume":0},{"time":1728543600,"open":27.655,"high":27.655,"low":27.655,"close":27.655,"volume":0},{"time":1728630000,"open":27.655,"high":27.655,"low":27.655,"close":27.655,"volume":0},{"time":1728889200,"open":27.655,"high":27.655,"low":27.655,"close":27.655,"volume":0},{"time":1728975600,"open":27.655,"high":27.655,"low":27.655,"close":27.655,"volume":0},{"time":1729062000,"open":27.655,"high":27.655,"low":27.655,"close":27.655,"volume":0},{"time":1729148400,"open":27.655,"high":27.655,"low":27.655,"close":27.655,"volume":0},{"time":1729234800,"open":27.655,"high":27.655,"low":27.655,"close":27.655,"volume":0},{"time":1729494000,"open":27.655,"high":27.655,"low":27.655,"close":27.655,"volume":0},{"time":1729580400,"open":27.655,"high":27.655,"low":27.655,"close":27.655,"volume":0},{"time":1729666800,"open":27.655,"high":27.655,"low":27.655,"close":27.655,"volume":0},{"time":1729753200,"open":27.655,"high":27.655,"low":27.655,"close":27.655,"volume":0},{"time":1729839600,"open":27.655,"high":27.655,"low":27.655,"close":27.655,"volume":0},{"time":1730102400,"open":27.655,"high":27.655,"low":27.655,"close":27.655,"volume":0},{"time":1730188800,"open":27.655,"high":27.655,"low":27.655,"close":27.655,"volume":0},{"time":1730275200,"open":27.655,"high":27.655,"low":27.655,"close":27.655,"volume":0},{"time":1730361600,"open":27.655,"high":27.655,"low":27.655,"close":27.655,"volume":0},{"time":1730448000,"open":27.655,"high":27.655,"low":27.655,"close":27.655,"volume":0},{"time":1730707200,"open":27.655,"high":27.655,"low":27.655,"close":27.655,"volume":0},{"time":1730793600,"open":27.655,"high":27.655,"low":27.655,"close":27.655,"volume":0},{"time":1730880000,"open":27.655,"high":27.655,"low":27.655,"close":27.655,"volume":0},{"time":1730966400,"open":27.655,"high":27.655,"low":27.655,"close":27.655,"volume":0},{"time":1731052800,"open":27.655,"high":27.655,"low":27.655,"close":27.655,"volume":0},{"time":1731312000,"open":27.655,"high":27.655,"low":27.655,"close":27.655,"volume":0},{"time":1731398400,"open":27.655,"high":27.655,"low":27.655,"close":27.655,"volume":0},{"time":1731484800,"open":27.655,"high":27.655,"low":27.655,"close":27.655,"volume":0},{"time":1731571200,"open":27.655,"high":27.655,"low":27.655,"close":27.655,"volume":0},{"time":1731657600,"open":27.655,"high":27.655,"low":27.655,"close":27.655,"volume":0},{"time":1731916800,"open":27.655,"high":27.655,"low":27.655,"close":27.655,"volume":0},{"time":1732003200,"open":27.655,"high":27.655,"low":27.655,"close":27.655,"volume":0},{"time":1732089600,"open":27.655,"high":27.655,"low":27.655,"close":27.655,"volume":0},{"time":1732176000,"open":27.655,"high":27.655,"low":27.655,"close":27.655,"volume":0},{"time":1732262400,"open":27.655,"high":27.655,"low":27.655,"close":27.655,"volume":0},{"time":1732521600,"open":27.655,"high":27.655,"low":27.655,"close":27.655,"volume":0},{"time":1732608000,"open":27.655,"high":27.655,"low":27.655,"close":27.655,"volume":0},{"time":1732694400,"open":27.655,"high":27.655,"low":27.655,"close":27.655,"volume":0},{"time":1732780800,"open":27.655,"high":27.655,"low":27.655,"close":27.655,"volume":0},{"time":1732867200,"open":27.655,"high":27.655,"low":27.655,"close":27.655,"volume":0},{"time":1733126400,"open":27.655,"high":27.655,"low":27.655,"close":27.655,"volume":0},{"time":1733212800,"open":27.655,"high":27.655,"low":27.655,"close":27.655,"volume":0},{"time":1733299200,"open":27.655,"high":27.655,"low":27.655,"close":27.655,"volume":0},{"time":1733385600,"open":27.655,"high":27.655,"low":27.655,"close":27.655,"volume":0},{"time":1733472000,"open":27.655,"high":27.655,"low":27.655,"close":27.655,"volume":0},{"time":1733731200,"open":27.655,"high":27.655,"low":27.655,"close":27.655,"volume":0},{"time":1733817600,"open":27.655,"high":27.655,"low":27.655,"close":27.655,"volume":0},{"time":1733904000,"open":27.655,"high":27.655,"low":27.655,"close":27.655,"volume":0},{"time":1733990400,"open":27.655,"high":27.655,"low":27.655,"close":27.655,"volume":0},{"time":1734076800,"open":27.655,"high":27.655,"low":27.655,"close":27.655,"volume":0},{"time":1734336000,"open":27.655,"high":27.655,"low":27.655,"close":27.655,"volume":0},{"time":1734422400,"open":27.955,"high":28.065,"low":28.065,"close":27.955,"volume":840},{"time":1734508800,"open":27.955,"high":27.955,"low":27.955,"close":27.955,"volume":0},{"time":1734595200,"open":27.955,"high":27.955,"low":27.955,"close":27.955,"volume":0},{"time":1734681600,"open":27.61,"high":27.505,"low":27.435,"close":27.61,"volume":708},{"time":1734940800,"open":27.61,"high":27.61,"low":27.61,"close":27.61,"volume":0},{"time":1735286400,"open":27.61,"high":27.61,"low":27.61,"close":27.61,"volume":0},{"time":1735545600,"open":27.61,"high":27.61,"low":27.61,"close":27.61,"volume":0},{"time":1735804800,"open":27.61,"high":27.61,"low":27.61,"close":27.61,"volume":0},{"time":1735891200,"open":27.61,"high":27.61,"low":27.61,"close":27.61,"volume":0},{"time":1736150400,"open":27.61,"high":27.61,"low":27.61,"close":27.61,"volume":0},{"time":1736236800,"open":27.61,"high":27.61,"low":27.61,"close":27.61,"volume":0},{"time":1736323200,"open":27.61,"high":27.61,"low":27.61,"close":27.61,"volume":0},{"time":1736409600,"open":27.61,"high":27.61,"low":27.61,"close":27.61,"volume":0},{"time":1736496000,"open":27.61,"high":27.61,"low":27.61,"close":27.61,"volume":0},{"time":1736755200,"open":27.61,"high":27.61,"low":27.61,"close":27.61,"volume":0},{"time":1736841600,"open":27.61,"high":27.61,"low":27.61,"close":27.61,"volume":0},{"time":1736928000,"open":27.61,"high":27.61,"low":27.61,"close":27.61,"volume":0},{"time":1737014400,"open":27.61,"high":27.61,"low":27.61,"close":27.61,"volume":0},{"time":1737100800,"open":27.61,"high":27.61,"low":27.61,"close":27.61,"volume":0},{"time":1737360000,"open":27.61,"high":27.61,"low":27.61,"close":27.61,"volume":0},{"time":1737446400,"open":27.61,"high":27.61,"low":27.61,"close":27.61,"volume":0},{"time":1737532800,"open":27.61,"high":27.61,"low":27.61,"close":27.61,"volume":0},{"time":1737619200,"open":27.61,"high":27.61,"low":27.61,"close":27.61,"volume":0},{"time":1737705600,"open":27.61,"high":27.61,"low":27.61,"close":27.61,"volume":0},{"time":1737964800,"open":27.61,"high":27.61,"low":27.61,"close":27.61,"volume":0},{"time":1738051200,"open":27.61,"high":27.61,"low":27.61,"close":27.61,"volume":0},{"time":1738137600,"open":27.61,"high":27.61,"low":27.61,"close":27.61,"volume":0},{"time":1738224000,"open":27.61,"high":27.61,"low":27.61,"close":27.61,"volume":0},{"time":1738310400,"open":27.61,"high":27.61,"low":27.61,"close":27.61,"volume":0},{"time":1738569600,"open":27.61,"high":27.61,"low":27.61,"close":27.61,"volume":0},{"time":1738656000,"open":27.61,"high":27.61,"low":27.61,"close":27.61,"volume":0},{"time":1738742400,"open":27.61,"high":27.61,"low":27.61,"close":27.61,"volume":0},{"time":1738828800,"open":27.61,"high":27.61,"low":27.61,"close":27.61,"volume":0},{"time":1738915200,"open":27.61,"high":27.61,"low":27.61,"close":27.61,"volume":0},{"time":1739174400,"open":28.63,"high":28.51,"low":28.455,"close":28.63,"volume":2577},{"time":1739260800,"open":28.63,"high":28.63,"low":28.63,"close":28.63,"volume":0},{"time":1739347200,"open":28.63,"high":28.63,"low":28.63,"close":28.63,"volume":0},{"time":1739433600,"open":28.63,"high":28.63,"low":28.63,"close":28.63,"volume":0},{"time":1739520000,"open":28.63,"high":28.63,"low":28.63,"close":28.63,"volume":0},{"time":1739779200,"open":28.63,"high":28.63,"low":28.63,"close":28.63,"volume":0},{"time":1739865600,"open":28.63,"high":28.63,"low":28.63,"close":28.63,"volume":0},{"time":1739952000,"open":28.63,"high":28.63,"low":28.63,"close":28.63,"volume":0},{"time":1740038400,"open":28.63,"high":28.63,"low":28.63,"close":28.63,"volume":0},{"time":1740124800,"open":28.63,"high":28.63,"low":28.63,"close":28.63,"volume":0},{"time":1740384000,"open":28.63,"high":28.63,"low":28.63,"close":28.63,"volume":0},{"time":1740470400,"open":28.63,"high":28.63,"low":28.63,"close":28.63,"volume":0},{"time":1740556800,"open":28.63,"high":28.63,"low":28.63,"close":28.63,"volume":0},{"time":1740643200,"open":28.63,"high":28.63,"low":28.63,"close":28.63,"volume":0},{"time":1740729600,"open":28.63,"high":28.63,"low":28.63,"close":28.63,"volume":0},{"time":1740988800,"open":28.63,"high":28.63,"low":28.63,"close":28.63,"volume":0},{"time":1741075200,"open":28.63,"high":28.63,"low":28.63,"close":28.63,"volume":0},{"time":1741161600,"open":28.63,"high":28.63,"low":28.63,"close":28.63,"volume":0},{"time":1741248000,"open":28.63,"high":28.63,"low":28.63,"close":28.63,"volume":0},{"time":1741334400,"open":27.035,"high":27.12,"low":27.12,"close":27.035,"volume":30},{"time":1741593600,"open":27.035,"high":27.035,"low":27.035,"close":27.035,"volume":0},{"time":1741680000,"open":27.035,"high":27.035,"low":27.035,"close":27.035,"volume":0},{"time":1741766400,"open":27.035,"high":27.035,"low":27.035,"close":27.035,"volume":0},{"time":1741852800,"open":27.035,"high":27.035,"low":27.035,"close":27.035,"volume":0},{"time":1741939200,"open":27.035,"high":27.035,"low":27.035,"close":27.035,"volume":0},{"time":1742198400,"open":27.035,"high":27.035,"low":27.035,"close":27.035,"volume":0},{"time":1742284800,"open":27.035,"high":27.035,"low":27.035,"close":27.035,"volume":0},{"time":1742371200,"open":27.035,"high":27.035,"low":27.035,"close":27.035,"volume":0},{"time":1742457600,"open":27.035,"high":27.035,"low":27.035,"close":27.035,"volume":0},{"time":1742544000,"open":27.035,"high":27.035,"low":27.035,"close":27.035,"volume":0},{"time":1742803200,"open":27.035,"high":27.035,"low":27.035,"close":27.035,"volume":0},{"time":1742889600,"open":27.035,"high":27.035,"low":27.035,"close":27.035,"volume":0},{"time":1742976000,"open":27.035,"high":27.035,"low":27.035,"close":27.035,"volume":0},{"time":1743062400,"open":27.035,"high":27.035,"low":27.035,"close":27.035,"volume":0},{"time":1743148800,"open":27.035,"high":27.035,"low":27.035,"close":27.035,"volume":0},{"time":1743404400,"open":27.035,"high":27.035,"low":27.035,"close":27.035,"volume":0},{"time":1743490800,"open":27.035,"high":27.035,"low":27.035,"close":27.035,"volume":0},{"time":1743577200,"open":27.035,"high":27.035,"low":27.035,"close":27.035,"volume":0},{"time":1743663600,"open":27.035,"high":27.035,"low":27.035,"close":27.035,"volume":0},{"time":1743750000,"open":27.035,"high":27.035,"low":27.035,"close":27.035,"volume":0},{"time":1744009200,"open":27.035,"high":27.035,"low":27.035,"close":27.035,"volume":0},{"time":1744095600,"open":27.035,"high":27.035,"low":27.035,"close":27.035,"volume":0},{"time":1744182000,"open":27.035,"high":27.035,"low":27.035,"close":27.035,"volume":0},{"time":1744268400,"open":27.035,"high":27.035,"low":27.035,"close":27.035,"volume":0},{"time":1744354800,"open":27.035,"high":27.035,"low":27.035,"close":27.035,"volume":0},{"time":1744614000,"open":27.035,"high":27.035,"low":27.035,"close":27.035,"volume":0},{"time":1744700400,"open":27.035,"high":27.035,"low":27.035,"close":27.035,"volume":0},{"time":1744786800,"open":27.035,"high":27.035,"low":27.035,"close":27.035,"volume":0},{"time":1744873200,"open":27.035,"high":27.035,"low":27.035,"close":27.035,"volume":0},{"time":1745305200,"open":27.035,"high":27.035,"low":27.035,"close":27.035,"volume":0},{"time":1745391600,"open":27.035,"high":27.035,"low":27.035,"close":27.035,"volume":0},{"time":1745478000,"open":27.035,"high":27.035,"low":27.035,"close":27.035,"volume":0},{"time":1745564400,"open":27.035,"high":27.035,"low":27.035,"close":27.035,"volume":0},{"time":1745823600,"open":27.035,"high":27.035,"low":27.035,"close":27.035,"volume":0},{"time":1745910000,"open":27.035,"high":27.035,"low":27.035,"close":27.035,"volume":0},{"time":1745996400,"open":25.205,"high":25.015,"low":25.015,"close":25.205,"volume":310},{"time":1746169200,"open":25.205,"high":25.205,"low":25.205,"close":25.205,"volume":0},{"time":1746428400,"open":25.205,"high":25.205,"low":25.205,"close":25.205,"volume":0},{"time":1746514800,"open":25.205,"high":25.205,"low":25.205,"close":25.205,"volume":0},{"time":1746601200,"open":25.205,"high":25.205,"low":25.205,"close":25.205,"volume":0},{"time":1746687600,"open":25.205,"high":25.205,"low":25.205,"close":25.205,"volume":0},{"time":1746774000,"open":25.205,"high":25.205,"low":25.205,"close":25.205,"volume":0},{"time":1747033200,"open":25.205,"high":25.205,"low":25.205,"close":25.205,"volume":0},{"time":1747119600,"open":25.205,"high":25.205,"low":25.205,"close":25.205,"volume":0},{"time":1747206000,"open":25.205,"high":25.205,"low":25.205,"close":25.205,"volume":0},{"time":1747292400,"open":25.205,"high":25.205,"low":25.205,"close":25.205,"volume":0},{"time":1747378800,"open":25.205,"high":25.205,"low":25.205,"close":25.205,"volume":0},{"time":1747638000,"open":25.205,"high":25.205,"low":25.205,"close":25.205,"volume":0},{"time":1747724400,"open":25.205,"high":25.205,"low":25.205,"close":25.205,"volume":0},{"time":1747810800,"open":25.205,"high":25.205,"low":25.205,"close":25.205,"volume":0},{"time":1747897200,"open":25.205,"high":25.205,"low":25.205,"close":25.205,"volume":0},{"time":1747983600,"open":25.205,"high":25.205,"low":25.205,"close":25.205,"volume":0},{"time":1748242800,"open":25.205,"high":25.205,"low":25.205,"close":25.205,"volume":0},{"time":1748329200,"open":25.205,"high":25.205,"low":25.205,"close":25.205,"volume":0},{"time":1748415600,"open":25.205,"high":25.205,"low":25.205,"close":25.205,"volume":0},{"time":1748502000,"open":25.205,"high":25.205,"low":25.205,"close":25.205,"volume":0},{"time":1748588400,"open":25.205,"high":25.205,"low":25.205,"close":25.205,"volume":0},{"time":1748847600,"open":25.205,"high":25.205,"low":25.205,"close":25.205,"volume":0},{"time":1748934000,"open":25.205,"high":25.205,"low":25.205,"close":25.205,"volume":0},{"time":1749020400,"open":25.205,"high":25.205,"low":25.205,"close":25.205,"volume":0},{"time":1749106800,"open":25.205,"high":25.205,"low":25.205,"close":25.205,"volume":0},{"time":1749193200,"open":25.205,"high":25.205,"low":25.205,"close":25.205,"volume":0},{"time":1749452400,"open":25.205,"high":25.205,"low":25.205,"close":25.205,"volume":0},{"time":1749538800,"open":25.205,"high":25.205,"low":25.205,"close":25.205,"volume":0},{"time":1749625200,"open":25.205,"high":25.205,"low":25.205,"close":25.205,"volume":0},{"time":1749711600,"open":25.205,"high":25.205,"low":25.205,"close":25.205,"volume":0},{"time":1749798000,"open":25.205,"high":25.205,"low":25.205,"close":25.205,"volume":0},{"time":1750057200,"open":25.205,"high":25.205,"low":25.205,"close":25.205,"volume":0},{"time":1750143600,"open":25.205,"high":25.205,"low":25.205,"close":25.205,"volume":0},{"time":1750230000,"open":25.205,"high":25.205,"low":25.205,"close":25.205,"volume":0},{"time":1750316400,"open":25.205,"high":25.205,"low":25.205,"close":25.205,"volume":0},{"time":1750402800,"open":25.205,"high":25.205,"low":25.205,"close":25.205,"volume":0},{"time":1750662000,"open":25.205,"high":25.205,"low":25.205,"close":25.205,"volume":0},{"time":1750748400,"open":25.205,"high":25.205,"low":25.205,"close":25.205,"volume":0},{"time":1750834800,"open":25.205,"high":25.205,"low":25.205,"close":25.205,"volume":0},{"time":1750921200,"open":25.205,"high":25.205,"low":25.205,"close":25.205,"volume":0},{"time":1751007600,"open":25.205,"high":25.205,"low":25.205,"close":25.205,"volume":0},{"time":1751266800,"open":25.205,"high":25.205,"low":25.205,"close":25.205,"volume":0},{"time":1751353200,"open":25.205,"high":25.205,"low":25.205,"close":25.205,"volume":0},{"time":1751439600,"open":25.205,"high":25.205,"low":25.205,"close":25.205,"volume":0},{"time":1751526000,"open":25.205,"high":25.205,"low":25.205,"close":25.205,"volume":0},{"time":1751612400,"open":25.205,"high":25.205,"low":25.205,"close":25.205,"volume":0},{"time":1751871600,"open":25.205,"high":25.205,"low":25.205,"close":25.205,"volume":0},{"time":1751958000,"open":25.205,"high":25.205,"low":25.205,"close":25.205,"volume":0},{"time":1752044400,"open":25.205,"high":25.205,"low":25.205,"close":25.205,"volume":0},{"time":1752130800,"open":25.205,"high":25.205,"low":25.205,"close":25.205,"volume":0},{"time":1752217200,"open":25.205,"high":25.205,"low":25.205,"close":25.205,"volume":0},{"time":1752476400,"open":25.205,"high":25.205,"low":25.205,"close":25.205,"volume":0},{"time":1752562800,"open":25.205,"high":25.205,"low":25.205,"close":25.205,"volume":0},{"time":1752649200,"open":25.205,"high":25.205,"low":25.205,"close":25.205,"volume":0},{"time":1752735600,"open":25.205,"high":25.205,"low":25.205,"close":25.205,"volume":0},{"time":1752822000,"open":25.205,"high":25.205,"low":25.205,"close":25.205,"volume":0},{"time":1753081200,"open":25.205,"high":25.205,"low":25.205,"close":25.205,"volume":0},{"time":1753167600,"open":25.205,"high":25.205,"low":25.205,"close":25.205,"volume":0},{"time":1753254000,"open":25.205,"high":25.205,"low":25.205,"close":25.205,"volume":0},{"time":1753340400,"open":25.205,"high":25.205,"low":25.205,"close":25.205,"volume":0},{"time":1753426800,"open":25.205,"high":25.205,"low":25.205,"close":25.205,"volume":0},{"time":1753686000,"open":25.205,"high":25.205,"low":25.205,"close":25.205,"volume":0},{"time":1753772400,"open":25.205,"high":25.205,"low":25.205,"close":25.205,"volume":0},{"time":1753858800,"open":25.205,"high":25.205,"low":25.205,"close":25.205,"volume":0},{"time":1753945200,"open":28.26,"high":28.23,"low":28.23,"close":28.26,"volume":369},{"time":1754031600,"open":28.26,"high":28.26,"low":28.26,"close":28.26,"volume":0},{"time":1754290800,"open":28.26,"high":28.26,"low":28.26,"close":28.26,"volume":0},{"time":1754377200,"open":28.26,"high":28.26,"low":28.26,"close":28.26,"volume":0},{"time":1754463600,"open":28.26,"high":28.26,"low":28.26,"close":28.26,"volume":0},{"time":1754550000,"open":28.26,"high":28.26,"low":28.26,"close":28.26,"volume":0},{"time":1754636400,"open":28.26,"high":28.26,"low":28.26,"close":28.26,"volume":0},{"time":1754895600,"open":28.26,"high":28.26,"low":28.26,"close":28.26,"volume":0},{"time":1754982000,"open":28.26,"high":28.26,"low":28.26,"close":28.26,"volume":0},{"time":1755068400,"open":28.26,"high":28.26,"low":28.26,"close":28.26,"volume":0},{"time":1755154800,"open":28.26,"high":28.26,"low":28.26,"close":28.26,"volume":0},{"time":1755500400,"open":28.645,"high":28.67,"low":28.67,"close":28.645,"volume":2},{"time":1755586800,"open":28.645,"high":28.645,"low":28.645,"close":28.645,"volume":0},{"time":1755673200,"open":28.645,"high":28.645,"low":28.645,"close":28.645,"volume":0},{"time":1755759600,"open":28.645,"high":28.645,"low":28.645,"close":28.645,"volume":0},{"time":1755846000,"open":28.645,"high":28.645,"low":28.645,"close":28.645,"volume":0},{"time":1756105200,"open":28.645,"high":28.645,"low":28.645,"close":28.645,"volume":0},{"time":1756191600,"open":28.645,"high":28.645,"low":28.645,"close":28.645,"volume":0},{"time":1756278000,"open":28.645,"high":28.645,"low":28.645,"close":28.645,"volume":0},{"time":1756364400,"open":28.645,"high":28.645,"low":28.645,"close":28.645,"volume":0},{"time":1756450800,"open":28.645,"high":28.645,"low":28.645,"close":28.645,"volume":0},{"time":1756710000,"open":28.645,"high":28.645,"low":28.645,"close":28.645,"volume":0},{"time":1756796400,"open":28.645,"high":28.645,"low":28.645,"close":28.645,"volume":0},{"time":1756882800,"open":28.35,"high":28.475,"low":28.475,"close":28.35,"volume":2},{"time":1756969200,"open":28.35,"high":28.35,"low":28.35,"close":28.35,"volume":0},{"time":1757055600,"open":28.35,"high":28.35,"low":28.35,"close":28.35,"volume":0},{"time":1757314800,"open":28.35,"high":28.35,"low":28.35,"close":28.35,"volume":0},{"time":1757401200,"open":28.35,"high":28.35,"low":28.35,"close":28.35,"volume":0},{"time":1757487600,"open":28.35,"high":28.35,"low":28.35,"close":28.35,"volume":0},{"time":1757574000,"open":28.35,"high":28.35,"low":28.35,"close":28.35,"volume":0},{"time":1757660400,"open":28.35,"high":28.35,"low":28.35,"close":28.35,"volume":0},{"time":1757919600,"open":28.35,"high":28.35,"low":28.35,"close":28.35,"volume":0},{"time":1758006000,"open":28.35,"high":28.35,"low":28.35,"close":28.35,"volume":0},{"time":1758092400,"open":28.35,"high":28.35,"low":28.35,"close":28.35,"volume":0},{"time":1758178800,"open":29.465,"high":29.44,"low":29.44,"close":29.465,"volume":2},{"time":1758265200,"open":29.465,"high":29.465,"low":29.465,"close":29.465,"volume":0},{"time":1758524400,"open":29.39,"high":29.32,"low":29.32,"close":29.39,"volume":350},{"time":1758610800,"open":29.39,"high":29.39,"low":29.39,"close":29.39,"volume":0},{"time":1758697200,"open":29.39,"high":29.39,"low":29.39,"close":29.39,"volume":0},{"time":1758783600,"open":29.39,"high":29.39,"low":29.39,"close":29.39,"volume":0},{"time":1758870000,"open":29.39,"high":29.39,"low":29.39,"close":29.39,"volume":0},{"time":1759129200,"open":29.39,"high":29.39,"low":29.39,"close":29.39,"volume":0},{"time":1759215600,"open":29.39,"high":29.39,"low":29.39,"close":29.39,"volume":0},{"time":1759302000,"open":29.39,"high":29.39,"low":29.39,"close":29.39,"volume":0},{"time":1759388400,"open":29.39,"high":29.39,"low":29.39,"close":29.39,"volume":0},{"time":1759474800,"open":30.485,"high":30.52,"low":30.52,"close":30.485,"volume":2},{"time":1759734000,"open":30.485,"high":30.485,"low":30.485,"close":30.485,"volume":0},{"time":1759820400,"open":30.485,"high":30.485,"low":30.485,"close":30.485,"volume":0},{"time":1759906800,"open":30.485,"high":30.485,"low":30.485,"close":30.485,"volume":0},{"time":1759993200,"open":30.825,"high":30.795,"low":30.795,"close":30.825,"volume":350},{"time":1760079600,"open":30.825,"high":30.825,"low":30.825,"close":30.825,"volume":0},{"time":1760338800,"open":30.825,"high":30.825,"low":30.825,"close":30.825,"volume":0},{"time":1760425200,"open":30.825,"high":30.825,"low":30.825,"close":30.825,"volume":0},{"time":1760511600,"open":30.825,"high":30.825,"low":30.825,"close":30.825,"volume":0},{"time":1760598000,"open":30.825,"high":30.825,"low":30.825,"close":30.825,"volume":0},{"time":1760684400,"open":30.825,"high":30.825,"low":30.825,"close":30.825,"volume":0},{"time":1760943600,"open":30.62,"high":30.62,"low":30.62,"close":30.62,"volume":2},{"time":1761030000,"open":30.62,"high":30.62,"low":30.62,"close":30.62,"volume":0},{"time":1761116400,"open":30.62,"high":30.62,"low":30.62,"close":30.62,"volume":0},{"time":1761202800,"open":30.62,"high":30.62,"low":30.62,"close":30.62,"volume":0},{"time":1761552000,"open":30.62,"high":30.62,"low":30.62,"close":30.62,"volume":0},{"time":1761638400,"open":30.62,"high":30.62,"low":30.62,"close":30.62,"volume":0},{"time":1761724800,"open":30.62,"high":30.62,"low":30.62,"close":30.62,"volume":0},{"time":1761811200,"open":30.62,"high":30.62,"low":30.62,"close":30.62,"volume":0},{"time":1761897600,"open":30.62,"high":30.62,"low":30.62,"close":30.62,"volume":0},{"time":1762156800,"open":30.83,"high":30.89,"low":30.89,"close":30.83,"volume":2},{"time":1762243200,"open":30.83,"high":30.83,"low":30.83,"close":30.83,"volume":0},{"time":1762329600,"open":30.83,"high":30.83,"low":30.83,"close":30.83,"volume":0},{"time":1762416000,"open":30.83,"high":30.83,"low":30.83,"close":30.83,"volume":0},{"time":1762502400,"open":30.83,"high":30.83,"low":30.83,"close":30.83,"volume":0},{"time":1762761600,"open":30.515,"high":30.515,"low":30.515,"close":30.515,"volume":2},{"time":1762848000,"open":30.425,"high":30.72,"low":30.72,"close":30.425,"volume":100},{"time":1762934400,"open":30.425,"high":30.425,"low":30.425,"close":30.425,"volume":0},{"time":1763020800,"open":30.425,"high":30.425,"low":30.425,"close":30.425,"volume":0},{"time":1763107200,"open":30.425,"high":30.425,"low":30.425,"close":30.425,"volume":0},{"time":1763366400,"open":30.425,"high":30.425,"low":30.425,"close":30.425,"volume":0},{"time":1763452800,"open":29.075,"high":29.1,"low":28.895,"close":29.075,"volume":42},{"time":1763539200,"open":29.075,"high":29.075,"low":29.075,"close":29.075,"volume":0},{"time":1763625600,"open":29.075,"high":29.075,"low":29.075,"close":29.075,"volume":0},{"time":1763712000,"open":29.075,"high":29.075,"low":29.075,"close":29.075,"volume":0},{"time":1763971200,"open":29.46,"high":29.46,"low":29.08,"close":29.46,"volume":29},{"time":1764057600,"open":29.46,"high":29.46,"low":29.46,"close":29.46,"volume":0},{"time":1764144000,"open":29.46,"high":29.46,"low":29.46,"close":29.46,"volume":0},{"time":1764230400,"open":29.46,"high":29.46,"low":29.46,"close":29.46,"volume":0},{"time":1764316800,"open":29.46,"high":29.46,"low":29.46,"close":29.46,"volume":0},{"time":1764576000,"open":29.46,"high":29.46,"low":29.46,"close":29.46,"volume":0},{"time":1764662400,"open":29.46,"high":29.46,"low":29.46,"close":29.46,"volume":0},{"time":1764748800,"open":30.19,"high":30.21,"low":30.21,"close":30.19,"volume":2},{"time":1764835200,"open":30.19,"high":30.19,"low":30.19,"close":30.19,"volume":0},{"time":1764921600,"open":30.19,"high":30.19,"low":30.19,"close":30.19,"volume":0},{"time":1765180800,"open":30.405,"high":30.405,"low":30.405,"close":30.405,"volume":2},{"time":1765267200,"open":30.405,"high":30.405,"low":30.405,"close":30.405,"volume":0},{"time":1765353600,"open":30.405,"high":30.405,"low":30.405,"close":30.405,"volume":0},{"time":1765440000,"open":30.405,"high":30.405,"low":30.405,"close":30.405,"volume":0},{"time":1765526400,"open":30.405,"high":30.405,"low":30.405,"close":30.405,"volume":0},{"time":1765785600,"open":30.005,"high":30.005,"low":30.005,"close":30.005,"volume":1},{"time":1765872000,"open":30.005,"high":30.005,"low":30.005,"close":30.005,"volume":0},{"time":1765958400,"open":30.005,"high":30.005,"low":30.005,"close":30.005,"volume":0},{"time":1766044800,"open":29.675,"high":29.705,"low":29.705,"close":29.675,"volume":2},{"time":1766131200,"open":29.675,"high":29.675,"low":29.675,"close":29.675,"volume":0},{"time":1766390400,"open":29.675,"high":29.675,"low":29.675,"close":29.675,"volume":0},{"time":1766476800,"open":29.885,"high":29.885,"low":29.885,"close":29.885,"volume":4},{"time":1766995200,"open":29.885,"high":29.885,"low":29.885,"close":29.885,"volume":0},{"time":1767081600,"open":29.885,"high":29.885,"low":29.885,"close":29.885,"volume":0},{"time":1767340800,"open":29.885,"high":29.885,"low":29.885,"close":29.885,"volume":0},{"time":1767600000,"open":30.705,"high":30.615,"low":30.615,"close":30.705,"volume":2},{"time":1767686400,"open":30.705,"high":30.705,"low":30.705,"close":30.705,"volume":0},{"time":1767772800,"open":30.705,"high":30.705,"low":30.705,"close":30.705,"volume":0},{"time":1767859200,"open":30.705,"high":30.705,"low":30.705,"close":30.705,"volume":0},{"time":1767945600,"open":30.705,"high":30.705,"low":30.705,"close":30.705,"volume":0},{"time":1768204800,"open":30.705,"high":30.705,"low":30.705,"close":30.705,"volume":0},{"time":1768291200,"open":30.705,"high":30.705,"low":30.705,"close":30.705,"volume":0},{"time":1768377600,"open":30.705,"high":30.705,"low":30.705,"close":30.705,"volume":0},{"time":1768464000,"open":31.57,"high":31.52,"low":31.52,"close":31.57,"volume":320},{"time":1768550400,"open":31.57,"high":31.57,"low":31.57,"close":31.57,"volume":0},{"time":1768809600,"open":31.57,"high":31.57,"low":31.57,"close":31.57,"volume":0},{"time":1768896000,"open":30.95,"high":30.785,"low":30.785,"close":30.95,"volume":2},{"time":1768982400,"open":30.95,"high":30.95,"low":30.95,"close":30.95,"volume":0},{"time":1769068800,"open":31.34,"high":31.375,"low":31.375,"close":31.34,"volume":280},{"time":1769155200,"open":30.85,"high":30.85,"low":30.85,"close":30.85,"volume":4},{"time":1769414400,"open":30.85,"high":30.85,"low":30.85,"close":30.85,"volume":0},{"time":1769500800,"open":30.85,"high":30.85,"low":30.85,"close":30.85,"volume":0},{"time":1769587200,"open":30.85,"high":30.85,"low":30.85,"close":30.85,"volume":0},{"time":1769673600,"open":30.85,"high":30.85,"low":30.85,"close":30.85,"volume":0},{"time":1769760000,"open":30.85,"high":30.85,"low":30.85,"close":30.85,"volume":0},{"time":1770019200,"open":31.535,"high":31.56,"low":31.04,"close":31.535,"volume":60},{"time":1770105600,"open":31.63,"high":31.605,"low":31.6,"close":31.63,"volume":6},{"time":1770192000,"open":31.63,"high":31.63,"low":31.63,"close":31.63,"volume":0},{"time":1770278400,"open":31.63,"high":31.63,"low":31.63,"close":31.63,"volume":0},{"time":1770364800,"open":31.63,"high":31.63,"low":31.63,"close":31.63,"volume":0},{"time":1770624000,"open":31.63,"high":31.63,"low":31.63,"close":31.63,"volume":0},{"time":1770710400,"open":31.63,"high":31.63,"low":31.63,"close":31.63,"volume":0},{"time":1770796800,"open":31.63,"high":31.63,"low":31.63,"close":31.63,"volume":0},{"time":1770883200,"open":31.63,"high":31.63,"low":31.63,"close":31.63,"volume":0},{"time":1770969600,"open":31.63,"high":31.63,"low":31.63,"close":31.63,"volume":0},{"time":1771228800,"open":32.68,"high":33.02,"low":33.02,"close":32.68,"volume":221},{"time":1771315200,"open":32.79,"high":32.79,"low":32.79,"close":32.79,"volume":75},{"time":1771401600,"open":32.945,"high":33.01,"low":33.01,"close":32.945,"volume":2},{"time":1771488000,"open":32.945,"high":32.945,"low":32.945,"close":32.945,"volume":0},{"time":1771574400,"open":32.945,"high":32.945,"low":32.945,"close":32.945,"volume":0},{"time":1771833600,"open":32.69,"high":32.69,"low":32.645,"close":32.69,"volume":643},{"time":1771920000,"open":32.96,"high":32.96,"low":32.96,"close":32.96,"volume":76},{"time":1772006400,"open":32.96,"high":32.96,"low":32.96,"close":32.96,"volume":0},{"time":1772092800,"open":32.96,"high":32.96,"low":32.96,"close":32.96,"volume":0},{"time":1772179200,"open":32.96,"high":32.96,"low":32.96,"close":32.96,"volume":0},{"time":1772438400,"open":32.96,"high":32.96,"low":32.96,"close":32.96,"volume":0},{"time":1772524800,"open":32.96,"high":32.96,"low":32.96,"close":32.96,"volume":0},{"time":1772611200,"open":32.24,"high":32.26,"low":32.26,"close":32.24,"volume":2},{"time":1772697600,"open":32.24,"high":32.24,"low":32.24,"close":32.24,"volume":0},{"time":1773043200,"open":31.71,"high":31.71,"low":31.71,"close":31.71,"volume":2},{"time":1773129600,"open":31.71,"high":31.71,"low":31.71,"close":31.71,"volume":0},{"time":1773216000,"open":31.71,"high":31.71,"low":31.71,"close":31.71,"volume":0},{"time":1773302400,"open":31.71,"high":31.71,"low":31.71,"close":31.71,"volume":0},{"time":1773388800,"open":31.71,"high":31.71,"low":31.71,"close":31.71,"volume":0},{"time":1773648000,"open":31.71,"high":31.71,"low":31.71,"close":31.71,"volume":0},{"time":1773734400,"open":31.71,"high":31.71,"low":31.71,"close":31.71,"volume":0},{"time":1773820800,"open":31.71,"high":31.71,"low":31.71,"close":31.71,"volume":0},{"time":1773907200,"open":31.71,"high":31.71,"low":31.71,"close":31.71,"volume":0},{"time":1773993600,"open":31.71,"high":31.71,"low":31.71,"close":31.71,"volume":0},{"time":1774252800,"open":31.71,"high":31.71,"low":31.71,"close":31.71,"volume":0},{"time":1774339200,"open":31.75,"high":31.75,"low":31.75,"close":31.75,"volume":4},{"time":1774425600,"open":31.75,"high":31.75,"low":31.75,"close":31.75,"volume":0},{"time":1774512000,"open":31.75,"high":31.75,"low":31.75,"close":31.75,"volume":0},{"time":1774598400,"open":31.75,"high":31.75,"low":31.75,"close":31.75,"volume":0},{"time":1774854000,"open":31.75,"high":31.75,"low":31.75,"close":31.75,"volume":0},{"time":1774940400,"open":31.75,"high":31.75,"low":31.75,"close":31.75,"volume":0},{"time":1775026800,"open":31.75,"high":31.75,"low":31.75,"close":31.75,"volume":0},{"time":1775113200,"open":31.75,"high":31.75,"low":31.75,"close":31.75,"volume":0},{"time":1775545200,"open":32.21,"high":32.315,"low":32.315,"close":32.21,"volume":2},{"time":1775631600,"open":33.65,"high":33.65,"low":33.65,"close":33.65,"volume":2},{"time":1775718000,"open":33.65,"high":33.65,"low":33.65,"close":33.65,"volume":0},{"time":1775804400,"open":33.65,"high":33.65,"low":33.65,"close":33.65,"volume":0},{"time":1776063600,"open":33.65,"high":33.65,"low":33.65,"close":33.65,"volume":0},{"time":1776150000,"open":33.65,"high":33.65,"low":33.65,"close":33.65,"volume":0},{"time":1776236400,"open":33.65,"high":33.65,"low":33.65,"close":33.65,"volume":0},{"time":1776322800,"open":33.65,"high":33.65,"low":33.65,"close":33.65,"volume":0},{"time":1776409200,"open":35.205,"high":34.845,"low":34.845,"close":35.205,"volume":144},{"time":1776668400,"open":35.245,"high":35.245,"low":35.245,"close":35.245,"volume":29},{"time":1776754800,"open":35.245,"high":35.245,"low":35.245,"close":35.245,"volume":0},{"time":1776841200,"open":35.245,"high":35.245,"low":35.245,"close":35.245,"volume":0},{"time":1776927600,"open":36.58,"high":36.58,"low":36.58,"close":36.58,"volume":2},{"time":1777014000,"open":36.97,"high":37.03,"low":37.03,"close":36.97,"volume":26},{"time":1777273200,"open":36.645,"high":37.06,"low":36.76,"close":36.645,"volume":20},{"time":1777359600,"open":36.645,"high":36.645,"low":36.645,"close":36.645,"volume":0},{"time":1777446000,"open":36.645,"high":36.645,"low":36.645,"close":36.645,"volume":0},{"time":1777532400,"open":36.645,"high":36.645,"low":36.645,"close":36.645,"volume":0},{"time":1777878000,"open":36.645,"high":36.645,"low":36.645,"close":36.645,"volume":0},{"time":1777964400,"open":36.645,"high":36.645,"low":36.645,"close":36.645,"volume":0},{"time":1778050800,"open":36.645,"high":36.645,"low":36.645,"close":36.645,"volume":0},{"time":1778137200,"open":38.515,"high":38.825,"low":38.795,"close":38.515,"volume":420},{"time":1778223600,"open":38.785,"high":38.785,"low":38.62,"close":38.785,"volume":3},{"time":1778482800,"open":38.785,"high":38.785,"low":38.785,"close":38.785,"volume":0},{"time":1778569200,"open":38.435,"high":38.605,"low":38.605,"close":38.435,"volume":220},{"time":1778655600,"open":39.555,"high":39.585,"low":39.32,"close":39.555,"volume":229},{"time":1778742000,"open":39.555,"high":39.555,"low":39.555,"close":39.555,"volume":0},{"time":1778828400,"open":39.555,"high":39.555,"low":39.555,"close":39.555,"volume":0},{"time":1779087600,"open":39.555,"high":39.555,"low":39.555,"close":39.555,"volume":0},{"time":1779174000,"open":39.555,"high":39.555,"low":39.555,"close":39.555,"volume":0},{"time":1779260400,"open":39.23,"high":39.29,"low":39.29,"close":39.23,"volume":210},{"time":1779346800,"open":39.23,"high":39.23,"low":39.23,"close":39.23,"volume":0},{"time":1779433200,"open":39.23,"high":39.23,"low":39.23,"close":39.23,"volume":0},{"time":1779692400,"open":40.735,"high":40.785,"low":40.785,"close":40.735,"volume":13},{"time":1779778800,"open":40.93,"high":40.93,"low":40.93,"close":40.93,"volume":12},{"time":1779865200,"open":40.545,"high":41.495,"low":40.805,"close":40.545,"volume":1305},{"time":1779951600,"open":40.545,"high":40.545,"low":40.545,"close":40.545,"volume":0},{"time":1780038000,"open":41.205,"high":41.685,"low":41.685,"close":41.205,"volume":350},{"time":1780297200,"open":41.185,"high":41.205,"low":41.005,"close":41.185,"volume":219},{"time":1780383600,"open":41.185,"high":41.185,"low":41.185,"close":41.185,"volume":0},{"time":1780470000,"open":42.25,"high":42.42,"low":42.235,"close":42.25,"volume":247},{"time":1780556400,"open":41.99,"high":42.06,"low":42.06,"close":41.99,"volume":190},{"time":1780642800,"open":41.385,"high":41.455,"low":41.2,"close":41.385,"volume":491},{"time":1780902000,"open":41.365,"high":41.38,"low":41.02,"close":41.365,"volume":20},{"time":1780988400,"open":41.365,"high":41.365,"low":41.365,"close":41.365,"volume":0},{"time":1781074800,"open":39.85,"high":39.905,"low":39.85,"close":39.85,"volume":2},{"time":1781161200,"open":39.85,"high":39.85,"low":39.85,"close":39.85,"volume":0},{"time":1781247600,"open":39.85,"high":39.85,"low":39.85,"close":39.85,"volume":0},{"time":1781506800,"open":41.705,"high":41.96,"low":41.625,"close":41.705,"volume":169},{"time":1781593200,"open":41.61,"high":41.94,"low":41.94,"close":41.61,"volume":28},{"time":1781679600,"open":41.61,"high":41.61,"low":41.61,"close":41.61,"volume":0},{"time":1781766000,"open":41.61,"high":41.61,"low":41.61,"close":41.61,"volume":0},{"time":1781852400,"open":42.105,"high":42.105,"low":42.025,"close":42.105,"volume":2},{"time":1782111600,"open":42.105,"high":42.105,"low":42.105,"close":42.105,"volume":0},{"time":1782198000,"open":42.105,"high":42.105,"low":42.105,"close":42.105,"volume":0},{"time":1782284400,"open":42.2,"high":42.29,"low":42.2,"close":42.2,"volume":122},{"time":1782370800,"open":41.64,"high":42.2,"low":42.2,"close":41.64,"volume":19},{"time":1782457200,"open":41.005,"high":41.2,"low":41.2,"close":41.005,"volume":208},{"time":1782716400,"open":40.93,"high":41.42,"low":41.42,"close":40.93,"volume":1},{"time":1782802800,"open":40.93,"high":40.93,"low":40.93,"close":40.93,"volume":0},{"time":1782889200,"open":40.93,"high":40.93,"low":40.93,"close":40.93,"volume":0},{"time":1782975600,"open":40.59,"high":41.195,"low":41.195,"close":40.59,"volume":10},{"time":1783062000,"open":40.955,"high":41.125,"low":41.125,"close":40.955,"volume":20},{"time":1783321200,"open":40.955,"high":40.955,"low":40.955,"close":40.955,"volume":0},{"time":1783407600,"open":40.1,"high":40.7,"low":40.65,"close":40.1,"volume":250},{"time":1783494000,"open":40.025,"high":40.025,"low":40.025,"close":40.025,"volume":1},{"time":1783580400,"open":40.025,"high":40.025,"low":40.025,"close":40.025,"volume":0},{"time":1783666800,"open":40.97,"high":41.065,"low":41.065,"close":40.97,"volume":10},{"time":1783926000,"open":40.97,"high":40.97,"low":40.97,"close":40.97,"volume":0},{"time":1784012400,"open":40.97,"high":40.97,"low":40.97,"close":40.97,"volume":0},{"time":1784098800,"open":40.97,"high":40.97,"low":40.97,"close":40.97,"volume":0},{"time":1784185200,"open":40.97,"high":40.97,"low":40.97,"close":40.97,"volume":0},{"time":1784271600,"open":40.97,"high":40.97,"low":40.97,"close":40.97,"volume":0}],"kama_v":[null,null,null,null,null,27.94,27.94,27.94,27.9459,27.9495,27.952,27.9533,27.9541,27.9541,27.4278,27.1355,26.973,26.8828,26.8327,26.8306,26.9659,27.041,27.0828,27.106,27.1189,27.1194,27.1199,27.1204,27.4647,27.7315,27.8797,27.9621,28.0078,27.7649,27.4738,27.4432,27.4641,27.483,27.5594,27.6019,27.6255,27.6265,27.6274,27.6283,27.6292,27.6301,27.6309,27.6317,27.6325,27.6332,27.6339,27.6346,27.6353,27.6359,27.6366,27.6372,27.6378,27.6383,27.6389,27.6394,27.6399,27.6404,27.6409,27.6414,27.6418,27.6423,27.6427,27.6431,27.6435,27.6439,27.6442,27.6446,27.6449,27.6453,27.6456,27.6459,27.6462,27.6465,27.6468,27.6471,27.6473,27.6476,27.6478,27.6481,27.6483,27.6485,27.6487,27.6489,27.6491,27.6493,27.6495,27.6497,27.6499,27.65,27.6502,27.6504,27.6505,27.6507,27.6508,27.6509,27.6511,27.6512,27.6513,27.6515,27.6516,27.7864,27.8613,27.903,27.8893,27.8764,27.758,27.6922,27.6557,27.6542,27.6527,27.6513,27.6499,27.6486,27.6473,27.6461,27.6449,27.6437,27.6426,27.6416,27.6405,27.6395,27.6385,27.6376,27.6367,27.6358,27.6349,27.6341,27.6333,27.6325,27.6318,27.6311,27.6304,27.6297,27.6291,28.0739,28.3211,28.4584,28.5346,28.577,28.5788,28.5805,28.5821,28.5837,28.5852,28.5867,28.5881,28.5895,28.5909,28.5922,28.5934,28.5946,28.5958,28.5969,27.9027,27.5171,27.3028,27.1838,27.1177,27.1149,27.1123,27.1097,27.1073,27.1049,27.1026,27.1003,27.0982,27.0961,27.0941,27.0921,27.0902,27.0884,27.0866,27.0849,27.0833,27.0817,27.0801,27.0786,27.0772,27.0758,27.0745,27.0732,27.0719,27.0707,27.0695,27.0684,27.0672,27.0662,27.0652,27.0642,26.2379,25.7788,25.5238,25.3821,25.3034,25.3001,25.297,25.294,25.291,25.2882,25.2854,25.2828,25.2802,25.2777,25.2753,25.273,25.2707,25.2686,25.2665,25.2644,25.2625,25.2606,25.2587,25.2569,25.2552,25.2536,25.252,25.2504,25.2489,25.2475,25.2461,25.2447,25.2434,25.2421,25.2409,25.2397,25.2386,25.2374,25.2364,25.2353,25.2343,25.2334,25.2324,25.2315,25.2306,25.2298,25.229,25.2282,25.2274,25.2267,25.226,25.2253,25.2246,25.2239,25.2233,25.2227,25.2221,25.2216,25.221,25.2205,25.22,25.2195,25.219,25.2185,25.2181,26.5701,27.3211,27.7384,27.9702,28.099,28.1043,28.1095,28.1145,28.1193,28.1239,28.1284,28.358,28.4856,28.5564,28.5958,28.6177,28.6186,28.6194,28.6203,28.6211,28.6219,28.6227,28.6234,28.5019,28.4344,28.3969,28.376,28.3645,28.364,28.3635,28.3631,28.3626,28.3622,28.3618,28.8521,29.1245,29.2219,29.2835,29.3226,29.3525,29.3692,29.3699,29.3705,29.3712,29.3718,29.8666,30.1414,30.2941,30.379,30.5772,30.6873,30.7485,30.7825,30.8014,30.8022,30.8029,30.7216,30.6765,30.6514,30.6374,30.6297,30.6294,30.6291,30.6288,30.6285,30.718,30.7678,30.7954,30.8108,30.8193,30.6841,30.5689,30.505,30.4694,30.4497,30.4387,29.8326,29.4959,29.3088,29.2049,29.2569,29.3472,29.3973,29.4252,29.4407,29.4413,29.4419,29.7744,29.9591,30.0617,30.2143,30.2991,30.3461,30.3723,30.3868,30.2171,30.1228,30.0705,29.8947,29.7971,29.7428,29.7547,29.7657,29.8187,29.8482,30.229,30.4405,30.5581,30.6234,30.6597,30.6612,30.6626,30.664,31.0667,31.2904,31.4147,31.3828,31.3531,31.352,31.2657,31.1943,31.175,31.1567,31.0204,31.0148,31.246,31.4167,31.5115,31.5642,31.5934,31.6097,31.6103,31.611,31.6116,31.6122,32.0868,32.3993,32.6419,32.7766,32.8514,32.8455,32.856,32.86,32.8639,32.8675,32.9086,32.9103,32.6124,32.4469,32.1194,31.9374,31.8364,31.7802,31.749,31.7477,31.7465,31.7453,31.7441,31.743,31.7419,31.7455,31.7475,31.7486,31.7492,31.7496,31.7496,31.7496,31.7496,31.9542,32.7079,33.1266,33.3592,33.4885,33.5603,33.5632,33.5661,34.2945,34.7169,34.9516,35.082,35.7478,36.291,36.3841,36.4528,36.5033,36.5106,36.5703,36.5728,36.5752,37.4373,38.0363,38.369,38.3876,38.7704,38.9449,39.0608,39.1546,39.3326,39.287,39.2617,39.2476,39.6112,39.9556,40.0958,40.2026,40.4849,40.5731,40.6274,41.3247,41.5125,41.5059,41.4987,41.4918,40.7621,40.3567,40.1315,40.2153,40.2804,40.7906,41.105,41.5006,41.6581,41.8567,42.0093,41.9953,41.6444,41.3879,41.2235,41.0931,40.8695,40.8734,40.8766,40.7264,40.5842,40.4977,40.514,40.5297,40.6858,40.8121,40.8823,40.8852],"kama_s":[null,null,null,null,null,null,null,null,null,null,null,null,null,null,null,null,null,null,null,null,null,27.135,27.135,27.135,27.135,27.135,27.135,27.135,27.1394,27.1471,27.1548,27.1623,27.1698,27.1671,27.1645,27.1718,27.2032,27.2327,27.2602,27.2859,27.3099,27.3228,27.3352,27.3472,27.3587,27.3698,27.3804,27.3907,27.4006,27.4064,27.4194,27.4318,27.4435,27.4546,27.5437,27.5932,27.6206,27.6208,27.6209,27.6211,27.6212,27.6214,27.6215,27.6216,27.6218,27.6219,27.622,27.6222,27.6223,27.6225,27.6226,27.6227,27.6229,27.623,27.6231,27.6233,27.6234,27.6235,27.6237,27.6238,27.6239,27.624,27.6242,27.6243,27.6244,27.6246,27.6247,27.6248,27.6249,27.6251,27.6252,27.6253,27.6254,27.6256,27.6257,27.6258,27.6259,27.626,27.6262,27.6263,27.6264,27.6265,27.6266,27.6268,27.6269,27.7727,27.8537,27.8987,27.8955,27.8922,27.889,27.8859,27.8827,27.8796,27.8766,27.8735,27.8706,27.8676,27.8647,27.8618,27.8589,27.8561,27.8533,27.8505,27.8478,27.8451,27.7406,27.6826,27.6503,27.6501,27.65,27.6498,27.6496,27.6495,27.6493,27.6492,27.649,27.6488,27.6487,28.0848,28.3271,28.4617,28.5365,28.5781,28.6011,28.614,28.6211,28.6251,28.6273,28.6285,28.6292,28.6295,28.6297,28.6299,28.6299,28.63,28.63,28.63,28.5681,28.5087,27.8537,27.4898,27.2877,27.1754,27.113,27.0783,27.0591,27.0484,27.0424,27.0391,27.0373,27.0363,27.0357,27.0354,27.0352,27.0351,27.0351,27.035,27.035,27.035,27.035,27.035,27.035,27.035,27.035,27.035,27.035,27.035,27.035,27.035,27.035,27.035,27.035,27.035,26.2217,25.7698,25.5188,25.3793,25.3018,25.2588,25.2349,25.2216,25.2142,25.2101,25.2078,25.2066,25.2059,25.2055,25.2053,25.2052,25.2051,25.205,25.205,25.205,25.205,25.205,25.205,25.205,25.205,25.205,25.205,25.205,25.205,25.205,25.205,25.205,25.205,25.205,25.205,25.205,25.205,25.205,25.205,25.205,25.205,25.205,25.205,25.205,25.205,25.205,25.205,25.205,25.205,25.205,25.205,25.205,25.205,25.205,25.205,25.205,25.205,25.205,25.205,25.205,25.205,25.205,25.205,25.205,25.205,26.5628,27.3171,27.7362,27.969,28.0983,28.1702,28.2101,28.2323,28.2446,28.2514,28.2552,28.4285,28.5247,28.5782,28.6079,28.6244,28.6335,28.6386,28.6415,28.643,28.6439,28.6444,28.6447,28.6385,28.6325,28.6267,28.6209,28.6153,28.6098,28.6044,28.5991,28.5939,28.4855,28.4253,28.6041,28.7521,28.8379,28.9121,28.9763,29.0319,29.08,29.1217,29.1578,29.189,29.2591,29.7413,30.0338,30.2112,30.3189,30.5212,30.6427,30.7155,30.7593,30.7856,30.8013,30.81,30.7681,30.7286,30.6997,30.6785,30.6629,30.6515,30.6431,30.6369,30.6324,30.6886,30.7049,30.7193,30.7321,30.7434,30.72,30.6821,30.6491,30.6204,30.5953,30.5734,30.12,29.8175,29.6026,29.4499,29.4513,29.4524,29.4534,29.4543,29.455,29.4557,29.4565,29.4855,29.5134,29.5401,29.5589,29.5655,29.5695,29.5735,29.5775,29.5867,29.5957,29.6573,29.6584,29.6593,29.6602,29.6692,29.6779,29.6862,29.6942,29.8122,29.9164,30.0084,30.0426,30.0751,30.1061,30.1228,30.1391,30.2965,30.4367,30.5614,30.5886,30.6139,30.6851,30.6973,30.7087,30.7192,30.7272,30.7347,30.7417,30.8236,30.8707,30.915,30.9567,30.996,31.0331,31.0679,31.1007,31.1316,31.1348,31.2435,31.3631,31.71,31.9809,32.1662,32.3167,32.5109,32.6465,32.7411,32.8072,32.8533,32.8809,32.8531,32.8266,32.8194,32.8123,32.8052,32.7982,32.7912,32.7843,32.7774,32.646,32.4952,32.3116,32.171,32.0815,32.021,31.9137,31.8488,31.8097,31.7861,31.7718,31.7632,31.7662,32.0801,32.7779,33.1655,33.3808,33.5005,33.5669,33.6038,34.3155,34.7286,34.9581,35.0856,35.7498,36.2921,36.4175,36.4983,36.5504,36.584,36.6057,36.6197,36.6287,37.3315,37.853,38.1874,38.2581,38.657,38.9332,39.1245,39.2569,39.3388,39.3152,39.2968,39.2823,39.6046,39.8907,40.0259,40.1332,40.3756,40.5563,40.6967,41.0837,41.2802,41.2909,41.2977,41.3039,41.2591,41.2473,41.2356,41.258,41.2735,41.2883,41.3068,41.3625,41.4143,41.4365,41.4593,41.4637,41.4591,41.4551,41.4512,41.4474,41.407,41.3957,41.3906,41.351,41.3078,41.2988,41.2893,41.2801,41.2719,41.265,41.2583,41.2517],"sar":[28.31,28.31,28.31,28.31,28.31,28.31,28.31,28.3017,28.2936,28.2856,28.2778,28.2701,28.2626,28.2553,28.2481,28.1903,28.1051,28.025,27.9497,27.8789,27.8124,27.7499,27.6911,27.6358,27.5838,27.535,27.4891,27.446,26.77,26.7934,26.8443,26.8931,26.94,26.985,27.0282,27.0696,27.1095,27.1477,27.1844,27.2196,27.2534,27.2859,27.317,27.347,27.3757,27.4033,27.4297,27.4551,27.4795,27.503,27.5254,27.547,27.5677,27.5876,27.6067,27.6251,27.6426,27.655,27.655,27.655,27.655,27.655,27.655,27.655,27.655,27.655,27.655,27.655,27.655,27.655,27.655,27.655,27.655,27.655,27.655,27.655,27.655,27.655,27.655,27.655,27.655,27.655,27.655,27.655,27.655,27.655,27.655,27.655,27.655,27.655,27.655,27.655,27.655,27.655,27.655,27.655,27.655,27.655,27.655,27.655,27.655,27.655,27.655,27.655,27.655,27.655,27.655,27.6714,28.065,28.0524,28.0401,28.028,28.0161,28.0045,27.9931,27.9819,27.971,27.9603,27.9498,27.9395,27.9294,27.9195,27.9098,27.9003,27.891,27.8819,27.8729,27.8642,27.8556,27.8472,27.8389,27.8309,27.8229,27.8152,27.8076,27.8001,27.7928,27.7857,27.7787,27.435,27.4565,27.5034,27.5485,27.5918,27.6333,27.6732,27.7114,27.7482,27.7834,27.8173,27.8498,27.881,27.911,27.9397,27.9674,27.9939,28.0193,28.0437,28.63,28.63,28.5662,28.505,28.4462,28.3897,28.3355,28.2835,28.2336,28.1856,28.1396,28.0954,28.053,28.0123,27.9732,27.9357,27.8996,27.865,27.8318,27.8,27.7694,27.74,27.7118,27.6847,27.6587,27.6338,27.6098,27.5868,27.5648,27.5436,27.5232,27.5037,27.485,27.467,27.4497,27.4331,27.4172,27.273,27.1376,27.0102,26.8905,26.778,26.6722,26.5728,26.4793,26.3914,26.3088,26.2312,26.1582,26.0896,26.0252,25.9646,25.9076,25.854,25.8037,25.7564,25.7119,25.6701,25.6308,25.5938,25.5591,25.5264,25.4958,25.4669,25.4398,25.4143,25.3904,25.3678,25.3467,25.3268,25.3081,25.2905,25.2739,25.2584,25.2438,25.2301,25.2172,25.205,25.205,25.205,25.205,25.205,25.205,25.205,25.205,25.205,25.205,25.205,25.205,25.205,25.205,25.205,25.205,25.205,25.205,25.205,25.205,25.205,25.205,25.205,25.205,25.015,25.0793,25.2065,25.3287,25.4459,25.5585,25.6665,25.7703,25.8699,25.9655,26.0573,26.1454,26.2968,26.4392,26.5731,26.6989,26.8172,26.9283,27.0328,27.1311,27.2234,27.3102,27.3918,27.4685,27.5406,27.6083,27.672,27.7319,27.7882,27.8411,27.8908,27.9376,27.9815,28.0228,28.0617,28.1719,28.3012,28.4176,28.5224,28.6166,28.7015,28.7778,28.8465,28.9084,28.964,29.0141,29.1948,29.3539,29.4938,29.6169,29.7819,29.9488,30.089,30.2067,30.3057,30.3888,30.4586,30.5172,30.5664,30.6078,30.62,30.62,30.62,30.62,30.62,30.62,30.62,30.6686,30.7085,30.7411,30.89,30.8825,30.8751,30.8571,30.8399,30.8233,30.8073,30.6926,30.5847,30.4834,30.3881,30.2985,30.2143,30.1351,30.0607,29.9908,29.925,28.895,28.9213,28.9471,28.9723,29.0296,29.0847,29.1375,29.1882,29.2368,29.2836,29.3284,29.3715,29.4128,29.4525,29.4906,29.5272,29.5623,29.596,29.6284,29.6876,29.769,29.8438,29.9127,29.9761,30.0344,30.0881,30.1374,30.2757,30.431,30.5677,30.688,30.785,31.57,31.5556,31.5415,31.5277,31.5141,31.5008,30.85,30.85,30.8802,30.9252,30.9675,31.0072,31.0446,31.0797,31.1127,31.1438,31.1729,31.3207,31.4567,31.5817,31.6968,31.8026,31.9,31.9896,32.0721,32.1479,32.2177,32.2818,33.02,33.0048,32.9742,32.8984,32.8271,32.76,32.697,32.6378,32.5821,32.5298,32.4806,32.4344,32.3909,32.3501,32.3117,32.2756,32.2416,32.2097,32.1797,32.1516,32.1251,31.71,31.7221,31.7992,31.8732,31.9443,32.0125,32.078,32.1409,32.2013,32.3599,32.5907,32.8031,32.9984,33.3566,33.7974,34.2541,34.647,34.9848,35.2753,35.5252,35.7401,35.9248,36.3889,36.7787,37.1061,37.3811,37.7778,38.1031,38.3698,38.5886,38.7679,38.915,39.0356,39.1345,39.23,39.57,39.955,40.263,40.545,40.773,40.9554,41.185,42.42,42.3956,42.3406,42.2878,42.1415,42.004,39.85,39.85,39.8922,39.9336,39.9741,40.0593,40.1411,40.2197,40.3439,40.4607,40.5704,40.6736,40.7706,40.8618,40.93,42.29,42.2633,42.1988,42.0683,41.9457,41.8305,41.7222,41.6203,41.5246,41.4346],"sar_trend":[1,1,1,1,1,-1,-1,-1,-1,-1,-1,-1,-1,-1,-1,-1,-1,-1,-1,-1,-1,-1,-1,-1,-1,-1,-1,-1,1,1,1,1,1,1,1,1,1,1,1,1,1,1,1,1,1,1,1,1,1,1,1,1,1,1,1,1,1,1,1,1,1,1,1,1,1,1,1,1,1,1,1,1,1,1,1,1,1,1,1,1,1,1,1,1,1,1,1,1,1,1,1,1,1,1,1,1,1,1,1,1,1,1,1,1,1,1,1,1,-1,-1,-1,-1,-1,-1,-1,-1,-1,-1,-1,-1,-1,-1,-1,-1,-1,-1,-1,-1,-1,-1,-1,-1,-1,-1,-1,-1,-1,-1,-1,1,1,1,1,1,1,1,1,1,1,1,1,1,1,1,1,1,1,1,-1,-1,-1,-1,-1,-1,-1,-1,-1,-1,-1,-1,-1,-1,-1,-1,-1,-1,-1,-1,-1,-1,-1,-1,-1,-1,-1,-1,-1,-1,-1,-1,-1,-1,-1,-1,-1,-1,-1,-1,-1,-1,-1,-1,-1,-1,-1,-1,-1,-1,-1,-1,-1,-1,-1,-1,-1,-1,-1,-1,-1,-1,-1,-1,-1,-1,-1,-1,-1,-1,-1,-1,-1,-1,-1,-1,-1,-1,-1,-1,-1,-1,-1,-1,-1,-1,-1,-1,-1,-1,-1,-1,-1,-1,-1,-1,-1,-1,-1,-1,-1,1,1,1,1,1,1,1,1,1,1,1,1,1,1,1,1,1,1,1,1,1,1,1,1,1,1,1,1,1,1,1,1,1,1,1,1,1,1,1,1,1,1,1,1,1,1,1,1,1,1,1,1,1,1,1,1,1,1,1,1,1,1,1,1,1,1,1,1,1,1,-1,-1,-1,-1,-1,-1,-1,-1,-1,-1,-1,-1,-1,-1,-1,-1,-1,1,1,1,1,1,1,1,1,1,1,1,1,1,1,1,1,1,1,1,1,1,1,1,1,1,1,1,1,1,1,1,1,-1,-1,-1,-1,-1,-1,1,1,1,1,1,1,1,1,1,1,1,1,1,1,1,1,1,1,1,1,1,1,-1,-1,-1,-1,-1,-1,-1,-1,-1,-1,-1,-1,-1,-1,-1,-1,-1,-1,-1,-1,-1,1,1,1,1,1,1,1,1,1,1,1,1,1,1,1,1,1,1,1,1,1,1,1,1,1,1,1,1,1,1,1,1,1,1,1,1,1,1,1,1,1,1,-1,-1,-1,-1,-1,-1,1,1,1,1,1,1,1,1,1,1,1,1,1,1,1,-1,-1,-1,-1,-1,-1,-1,-1,-1,-1],"ao":[0.0,0.0,0.0,0.0,0.0,-0.08003552300589334,-0.12681012066042996,-0.15807487013527322,-0.15622902054316157,-0.1714954400390276,-0.17984104468197515,-0.18317342161260441,-0.1829131249905096,-0.18011601345073558,-0.39735061081486833,-0.5520400379401984,-0.653541275151106,-0.7159808461052322,-0.7499062449070024,-0.7631834019895827,-0.6932054313239782,-0.6318894589071746,-0.5795033147137616,-0.5341802082525113,-0.4944991514227297,-0.45937470192991725,-0.4279742026181452,-0.3996556466388448,-0.21867095681759707,-0.06345791248946853,0.04720642474956094,0.12478754287216631,0.17786579721783724,0.07303726354714613,-0.04649192931623958,-0.09081627427895,-0.09000542944054502,-0.05343190988604718,-0.026805893774135114,-0.007594555326797092,0.006099099079918346,0.015695338994952124,0.022257032377801522,0.026579129378848876,0.029255767552747614,0.030730593582109833,0.03133449779455688,0.031313908662006895,0.030852007651677837,0.030084634685060507,0.02911221187745383,0.0280086812938265,0.026828203505491643,0.02561017701937729,0.024382998618207807,0.023166879625691195,0.02197595434347477,0.02081985783185658,0.019704905901047454,0.01863497695138605,0.01761217038053431,0.016637297585710087,0.015710247572432223,0.014830258669149998,0.013996119963699982,0.013206320165366492,0.012459157162755474,0.011752818222866779,0.011085438283622295,0.010455141922534494,0.00986007318258686,0.009298416385302488,0.008768410273148675,0.00826835723279018,0.00779662890806776,0.007351669179758602,0.006931995240744726,0.006536197309003455,0.0061629373814291455,0.005810947327194782,0.005479026541312493,0.005166039320705806,0.004870912081553769,0.004592630504131279,0.004330236667179577,0.004082826215807245,0.0038495455935390055,0.0036295893593134565,0.0034221976028376844,0.0032266534664309177,0.0030422807775956073,0.0028684417936695183,0.0027045350579832927,0.002549993365491332,0.0024042818348632977,0.0022668960834266727,0.0021373605008605523,0.002015226617462673,0.0019000715625239195,0.0017914966084973116,0.001689125796598745,0.0015926046396650406,0.0015015988981232908,0.0014157934252025939,0.0013348910775654588,0.08033001083153479,0.11382887050644541,0.13589122312647106,0.05601532300959278,0.025731682019099367,0.003949226146978901,-0.011510499450405831,-0.022278298273548103,-0.029574408894578852,-0.034311309849528016,-0.03717081395553379,-0.03866188023113182,-0.03916396452271442,-0.03895952463572527,-0.038258391792272306,-0.03721604225594177,-0.035947294480163094,-0.03453657577471958,-0.03304561646480053,-0.03151921500328925,-0.02998955661260183,-0.028479447370436617,-0.027004735158186577,-0.025576121020119302,-0.024200513579341276,-0.022882040980800156,-0.021622806200678468,-0.020423450089012363,-0.019283570408777706,-0.018202033057626466,-0.017177202601345698,-0.01620711245581674,-0.015289589960680416,-0.014422347768249466,0.1546647040391207,0.3004701611934948,0.39928301787846365,0.46345378056457065,0.5022109087416844,0.5224432935420467,0.5292870043145612,0.5265652425849154,0.5171182076105936,0.5030504013414578,0.4859160183176918,0.46685790434634455,0.4467116965473714,0.4260838539388523,0.40541011018084205,0.38499924694938414,0.3650658615650002,0.34575488387797293,0.32715990845817444,0.01812292942337379,-0.21706231030853473,-0.3802709825431201,-0.49025038672981935,-0.5610179598799867,-0.6030462014664622,-0.6241512265673776,-0.6301590482234936,-0.6254051642771223,-0.6131091297110878,-0.5956553748435205,-0.5748037142608347,-0.551847129787923,-0.5277300146279664,-0.503136768698738,-0.4785581623816597,-0.4543410313091307,-0.4307254738891402,-0.4078726800865873,-0.385885737610689,-0.36482517489400834,-0.3447205601887262,-0.32557914607301086,-0.307392301147285,-0.2901402850762729,-0.2737957839249674,-0.2583265183404748,-0.24369715884371956,-0.22987072378753126,-0.2168095915151227,-0.20447622524370246,-0.19283368444828852,-0.18184597796512492,-0.17147830012395815,-0.16169718079164852,-0.15247057239534811,-0.5333394079924538,-0.758405990053685,-0.9067258446533621,-0.9986559440537981,-1.0493971437147671,-1.0702870328505263,-1.069769353984377,-1.0541208617292526,-1.0279962727527092,-0.9948367952228274,-0.9571763533235149,-0.9168710929329507,-0.875271357472009,-0.8333505251464572,-0.7918015004998651,-0.7511089544926328,-0.7116033833233395,-0.6735015382347207,-0.6369366400901271,-0.6019809386865909,-0.5686625364271372,-0.536977915737566,-0.5069012494536871,-0.47839130330360646,-0.4513965370502824,-0.4258588589561434,-0.40171637431877016,-0.3789053834063587,-0.35736182006963446,-0.33702227428052467,-0.31782470583993216,-0.29970892950208494,-0.2826169315274356,-0.2664930625092552,-0.2512841399534089,-0.23693948557529865,-0.2234109158997022,-0.21065269997339087,-0.1986214944258755,-0.1872762634397631,-0.17657818919330381,-0.16649057684482926,-0.1569787570149117,-0.1480099878921095,-0.13955335847110106,-0.13157969397380143,-0.12406146416536856,-0.11697269502704088,-0.11028888406455195,-0.10398691939729687,-0.09804500267691907,-0.09244257581498161,-0.08716025145096751,-0.08217974705854658,-0.07748382256592379,-0.07305622135234202,-0.0688816144748472,-0.0649455479761194,-0.061234393123786646,-0.05773529943358113,-0.05443615033217242,-0.05132552131999901,-0.04839264049967795,-0.045627351341025246,-0.04302007755967807,0.5428309935816777,0.9551425121192487,1.2330607643405394,1.4119735174921608,1.5183193426852064,1.5718307570333607,1.5872162463647932,1.5754214674439488,1.5445748528150105,1.5006965345729029,1.4482297733220868,1.4695106802481739,1.4587449568543818,1.4302928387851388,1.3897403718820982,1.3412105506880607,1.2877328835481627,1.2315203491628353,1.1741769091451708,1.1168529492877504,1.060361678398749,1.0052662557215442,0.9519449746037836,0.8678542686051962,0.7718850655261207,0.6929941995555424,0.6273071700541273,0.5718955253344973,0.52454164049227,0.4835622270610891,0.4476758957481657,0.41590376295191334,0.38749484386096356,0.3618700390200651,0.5487943844670937,0.677958035400227,0.7316456997713736,0.7726584078674819,0.790622274194483,0.792030690037226,0.7817119170969171,0.7632477574163161,0.7392874193933743,0.7117827886572456,0.6821647599415925,0.8694041490585853,0.9826391158038561,1.0486747120622404,1.0803902449583518,1.1471691224386547,1.1837890450465238,1.19277328967571,1.182086815668125,1.1576429973960742,1.1238199687980384,1.0838476847351721,1.0005623316511887,0.9273739415182121,0.8623710950453471,0.8040852093960318,0.7513818301240747,0.7033789857799881,0.6593858460541,0.618856613732877,0.5813558478238292,0.598603514542134,0.5906772745105862,0.5766340437095572,0.5584658441615495,0.5376402481360074,0.4544828986906033,0.4287218597447975,0.3474876552086492,0.28507935835510523,0.2368752147464548,0.19940406726967197,-0.10524535991407191,-0.3042260263544172,-0.44058769724645686,-0.5307207688451641,-0.5492691012704114,-0.5178959443933309,-0.48831212711034766,-0.46041625450152424,-0.43411251237811754,-0.409310401699738,-0.3859244748385997,-0.2192312197748123,-0.10208026384868418,-0.01777951267450817,0.0835514695502475,0.15401335741560374,0.20163978730017007,0.2324379086142514,0.25089603856329035,0.18322119277113558,0.13274796334995287,0.0951597802114037,0.00936314384158976,-0.05722694064214906,-0.10349811551790467,-0.09423971053568536,-0.08634641400489329,-0.0795312055437627,-0.07357571948134023,0.07247236765811493,0.19207108202499157,0.27390058601264045,0.32785286974658234,0.36132122939063294,0.3798264090047745,0.3874861230318487,0.38736711905053767,0.5389278246741469,0.6480466361600286,0.7159514151941906,0.6023490895789543,0.5452326346087517,0.5790182423899495,0.49338787799881345,0.4257865792079585,0.3719001382171676,0.3284818672562899,0.29308634897315144,0.2638697132018919,0.3262254880761759,0.42399880633755416,0.49238480109374905,0.5337094002271456,0.5553073753253734,0.5626472666401909,0.5597998002608087,0.5497890947459467,0.53485596592121,0.5166553110248415,0.7644757364686363,0.8844420436516138,0.9990685456942572,1.0533180006206244,1.0766327151668307,1.0242211950944586,1.0289376576875107,1.0175737611256253,0.9950010948264989,0.9648246937317424,0.929702457332855,0.8915845550603123,0.7168926833855451,0.5792627546329285,0.37144876539281313,0.21918817635312138,0.10838692872714972,0.028486233209825684,-0.028421919094711257,-0.06825808509442055,-0.09545282983572534,-0.11331978747656635,-0.12433542484435023,-0.1303488337709382,-0.1327390467437226,-0.12481853439786406,-0.11743447874760804,-0.11053526112710443,-0.10407745350793363,-0.0980240402128345,-0.09234306880825471,-0.0870066237606153,-0.08199004299463297,0.03169270345511066,0.36909473752083954,0.6024133939313074,0.7587971096225417,0.8585427784381636,0.9168123188372448,0.9449198892789212,0.9512971013872544,1.1726809696458673,1.389620821218827,1.5231765616708657,1.5958598843952245,1.8819242233845728,2.1441130713539707,2.2757452045352125,2.2852102563592425,2.259257539343963,2.208630153178248,2.141277499344234,2.0630598727138363,1.9782765528435675,2.307597063186293,2.486775879883581,2.593866333118463,2.5978250042918205,2.726958963704014,2.799086597801413,2.810104187658851,2.7777508520914793,2.7151902669103904,2.581055538429986,2.4377592078922916,2.3016030997564627,2.4723341521477877,2.5857107110196864,2.6713738493543246,2.5771085911945164,2.6934915110311124,2.625455283186085,2.5552660033077643,2.689467258501203,2.6943568535404694,2.5180558116966765,2.332824174657503,2.2003344911078315,1.788336419314298,1.4661436616995758,1.2173624450763114,1.3986728986709949,1.53535050145166,1.5464250388140428,1.5321645325372444,1.5879422379199966,1.6124142491905502,1.606684967886288,1.6066811552721916,1.5750472851345094,1.3373198014637921,1.1925360120054336,0.9786173727042566,0.8133660867312145,0.7359973298434568,0.6572723773304006,0.5594276229377115,0.42824544815070453,0.20400604886118145,0.04252238723699975,0.12829377614517767,0.16879270462704454,0.19501990827311744,0.2107802893046582,0.21891398318690136,0.22153832410095475],"signals":["NONE","NONE","NONE","NONE","NONE","NONE","NONE","NONE","NONE","NONE","NONE","NONE","NONE","NONE","NONE","NONE","NONE","NONE","NONE","NONE","NONE","NONE","NONE","NONE","NONE","NONE","NONE","NONE","NONE","NONE","NONE","NONE","NONE","NONE","NONE","NONE","NONE","NONE","NONE","NONE","BUY1","WATCH","WATCH","WATCH","WATCH","WATCH","WATCH","WATCH","WATCH","WATCH","WATCH","WATCH","WATCH","WATCH","WATCH","WATCH","WATCH","WATCH","WATCH","WATCH","WATCH","WATCH","WATCH","WATCH","WATCH","WATCH","WATCH","WATCH","WATCH","WATCH","WATCH","WATCH","WATCH","WATCH","WATCH","WATCH","WATCH","WATCH","WATCH","WATCH","WATCH","WATCH","WATCH","WATCH","WATCH","WATCH","WATCH","WATCH","WATCH","WATCH","WATCH","WATCH","WATCH","WATCH","WATCH","WATCH","WATCH","WATCH","WATCH","WATCH","WATCH","WATCH","WATCH","WATCH","WATCH","WATCH","BUY2","BUY3","NONE","NONE","NONE","NONE","NONE","NONE","NONE","NONE","NONE","NONE","NONE","NONE","NONE","NONE","NONE","NONE","NONE","NONE","NONE","NONE","NONE","NONE","NONE","NONE","NONE","NONE","NONE","NONE","NONE","NONE","NONE","WATCH","BUY2","BUY3","BUY3","BUY3","WATCH","WATCH","WATCH","WATCH","WATCH","WATCH","WATCH","WATCH","WATCH","WATCH","WATCH","WATCH","WATCH","WATCH","NONE","NONE","NONE","NONE","NONE","NONE","NONE","NONE","NONE","NONE","NONE","NONE","NONE","NONE","NONE","NONE","NONE","NONE","NONE","NONE","NONE","NONE","NONE","NONE","NONE","NONE","NONE","NONE","NONE","NONE","NONE","NONE","NONE","NONE","NONE","NONE","NONE","NONE","NONE","NONE","NONE","NONE","NONE","NONE","NONE","NONE","NONE","NONE","NONE","NONE","NONE","NONE","NONE","NONE","NONE","NONE","NONE","NONE","NONE","NONE","NONE","NONE","NONE","NONE","NONE","NONE","NONE","NONE","NONE","NONE","NONE","NONE","NONE","NONE","NONE","NONE","NONE","NONE","NONE","NONE","NONE","NONE","NONE","NONE","NONE","NONE","NONE","NONE","NONE","NONE","NONE","NONE","NONE","NONE","NONE","NONE","NONE","NONE","NONE","NONE","NONE","WATCH","BUY2","BUY3","BUY3","BUY3","BUY3","BUY3","BUY1","BUY1","BUY1","WATCH","BUY1","BUY1","BUY1","BUY1","BUY1","WATCH","WATCH","WATCH","WATCH","WATCH","WATCH","WATCH","NONE","NONE","NONE","NONE","NONE","NONE","NONE","NONE","NONE","NONE","NONE","WATCH","BUY2","BUY3","BUY3","BUY3","BUY3","BUY1","WATCH","WATCH","WATCH","WATCH","WATCH","BUY2","BUY3","BUY3","BUY3","BUY3","BUY3","BUY1","BUY1","WATCH","WATCH","NONE","NONE","NONE","NONE","NONE","NONE","NONE","NONE","NONE","WATCH","BUY1","BUY1","BUY1","BUY1","NONE","NONE","NONE","NONE","NONE","NONE","NONE","NONE","NONE","NONE","NONE","NONE","NONE","NONE","NONE","NONE","NONE","WATCH","BUY1","BUY1","BUY3","BUY3","BUY3","BUY3","BUY3","WATCH","WATCH","WATCH","WATCH","WATCH","WATCH","WATCH","BUY1","BUY1","BUY1","BUY3","BUY3","BUY3","BUY3","BUY3","WATCH","WATCH","WATCH","WATCH","BUY2","BUY3","WATCH","WATCH","WATCH","NONE","NONE","NONE","NONE","NONE","NONE","WATCH","BUY2","BUY2","WATCH","BUY3","BUY3","WATCH","WATCH","WATCH","WATCH","WATCH","BUY2","BUY3","BUY3","BUY3","WATCH","WATCH","BUY1","BUY1","BUY1","BUY1","WATCH","NONE","NONE","NONE","NONE","NONE","NONE","NONE","NONE","NONE","NONE","NONE","NONE","NONE","NONE","NONE","NONE","NONE","NONE","NONE","NONE","NONE","WATCH","BUY2","BUY3","BUY3","BUY3","BUY3","WATCH","WATCH","WATCH","BUY2","BUY3","BUY3","BUY3","BUY3","BUY3","BUY3","BUY1","BUY1","BUY1","WATCH","WATCH","WATCH","BUY2","BUY3","BUY3","BUY3","BUY3","BUY3","BUY1","BUY1","NONE","NONE","NONE","WATCH","BUY2","BUY2","BUY1","BUY1","BUY1","BUY1","BUY1","BUY2","NONE","NONE","NONE","NONE","NONE","NONE","WATCH","WATCH","WATCH","WATCH","WATCH","WATCH","WATCH","BUY1","WATCH","NONE","NONE","NONE","NONE","NONE","NONE","NONE","NONE","NONE","NONE","NONE","NONE","NONE","NONE","NONE","NONE"],"uscite":["","","","","","","","","","","","","","","","","","","","","","","","","","","","","","","","","","","","","","","","","","","","","","","","","","","","","","","","","","","","","","","","","","","","","","","","","","","","","","","","","","","","","","","","","","","","","","","","","","","","","","","","","","","","","STOP","STOP","STOP","STOP","STOP","STOP","STOP","STOP","STOP","STOP","STOP","STOP","STOP","STOP","STOP","STOP","STOP","STOP","STOP","STOP","STOP","STOP","STOP","STOP","STOP","STOP","STOP","STOP","STOP","STOP","STOP","","","","","","","","","","","","","","","","","","","","STOP","STOP","STOP","STOP","STOP","STOP","STOP","STOP","STOP","STOP","STOP","STOP","STOP","STOP","STOP","STOP","STOP","STOP","STOP","STOP","STOP","STOP","STOP","STOP","STOP","STOP","STOP","STOP","STOP","STOP","STOP","STOP","STOP","STOP","STOP","STOP","STOP","STOP","STOP","STOP","STOP","STOP","STOP","STOP","STOP","STOP","STOP","STOP","STOP","STOP","STOP","STOP","STOP","STOP","STOP","STOP","STOP","STOP","STOP","STOP","STOP","STOP","STOP","STOP","STOP","STOP","STOP","STOP","STOP","STOP","STOP","STOP","STOP","STOP","STOP","STOP","STOP","STOP","STOP","STOP","STOP","STOP","STOP","STOP","STOP","STOP","STOP","STOP","STOP","STOP","STOP","STOP","STOP","STOP","STOP","STOP","STOP","STOP","STOP","STOP","STOP","","","","","","","","","","","","","","","","","","","","","","","","USCITA","USCITA","USCITA","USCITA","USCITA","USCITA","USCITA","USCITA","USCITA","USCITA","USCITA","","","","","","","","","","","","","","","","","","","","","","","USCITA","USCITA","USCITA","USCITA","USCITA","USCITA","USCITA","USCITA","USCITA","","","","","","STOP","STOP","STOP","STOP","STOP","STOP","STOP","STOP","STOP","STOP","ATTENZIONE","ATTENZIONE","ATTENZIONE","ATTENZIONE","ATTENZIONE","ATTENZIONE","ATTENZIONE","","","","","","","","","","","","","","","","","","","","","","","","","","","","","","","","","ATTENZIONE","ATTENZIONE","ATTENZIONE","ATTENZIONE","ATTENZIONE","ATTENZIONE","","","","","","","","","","","","","","","","","","","","","","","STOP","STOP","STOP","STOP","STOP","STOP","STOP","STOP","STOP","STOP","STOP","STOP","STOP","STOP","STOP","STOP","STOP","STOP","STOP","STOP","STOP","","","","","","","","","","","","","","","","","","","","","","","","","","","","","","","USCITA","USCITA","USCITA","","","","","","","","","","ATTENZIONE","ATTENZIONE","ATTENZIONE","STOP","STOP","STOP","","","","","","","","","","USCITA","USCITA","USCITA","USCITA","USCITA","USCITA","STOP","STOP","STOP","STOP","STOP","STOP","STOP","STOP","STOP","STOP"],"perf":{"trades":9,"closed":9,"wins":4,"wr":44.4,"totalPnl":22.22,"best":21.79,"worst":-5.57,"avg":2.47,"dd":5.73},"trades":[{"entSig":"BUY1","exitSig":"STOP","entTime":1726556400,"exitTime":1734681600,"entPrice":27.655,"exitPrice":27.61,"pnlPct":-0.1627,"isOpen":false,"days":68},{"entSig":"WATCH","exitSig":"STOP","entTime":1739174400,"exitTime":1741334400,"entPrice":28.63,"exitPrice":27.035,"pnlPct":-5.5711,"isOpen":false,"days":19},{"entSig":"WATCH","exitSig":"USCITA","entTime":1753945200,"exitTime":1756882800,"entPrice":28.26,"exitPrice":28.35,"pnlPct":0.3185,"isOpen":false,"days":23},{"entSig":"WATCH","exitSig":"USCITA","entTime":1758178800,"exitTime":1760943600,"entPrice":29.465,"exitPrice":30.62,"pnlPct":3.9199,"isOpen":false,"days":22},{"entSig":"WATCH","exitSig":"STOP","entTime":1762156800,"exitTime":1762761600,"entPrice":30.83,"exitPrice":30.515,"pnlPct":-1.0217,"isOpen":false,"days":5},{"entSig":"WATCH","exitSig":"STOP","entTime":1764748800,"exitTime":1772611200,"entPrice":30.19,"exitPrice":32.24,"pnlPct":6.7903,"isOpen":false,"days":60},{"entSig":"WATCH","exitSig":"USCITA","entTime":1775545200,"exitTime":1779260400,"entPrice":32.21,"exitPrice":39.23,"pnlPct":21.7945,"isOpen":false,"days":30},{"entSig":"WATCH","exitSig":"STOP","entTime":1779692400,"exitTime":1781074800,"entPrice":40.735,"exitPrice":39.85,"pnlPct":-2.1726,"isOpen":false,"days":12},{"entSig":"WATCH","exitSig":"USCITA","entTime":1781506800,"exitTime":1782457200,"entPrice":41.705,"exitPrice":41.005,"pnlPct":-1.6785,"isOpen":false,"days":9}]}